<?xml version="1.0" encoding="UTF-8"?>
<mets xmlns:xsi="http://www.w3.org/2001/XMLSchema-instance" xmlns="http://www.loc.gov/METS/" xsi:schemaLocation="http://www.loc.gov/METS/ //docstorage/impdata$/docWORKS/schema/mets-metae.xsd" xmlns:MODS="http://www.loc.gov/mods/v3" xmlns:mix="http://www.loc.gov/mix/" xmlns:xlink="http://www.w3.org/TR/xlink" TYPE="Newspaper" LABEL="Oxford Observer no.  1895-03-23">
	<metsHdr CREATEDATE="2009-01-23T18:36:53" LASTMODDATE="2009-01-23T18:36:53">
		<agent ROLE="CREATOR" TYPE="OTHER" OTHERTYPE="SOFTWARE">
			<name>CCS docWORKS/METAe Version 6.2-1</name>
		</agent>
	</metsHdr>
	<dmdSec ID="MODSMD_PRINT">
		<mdWrap MIMETYPE="text/xml" MDTYPE="MODS" LABEL="Bibliographic meta-data of the printed version">
			<xmlData>
				<MODS:mods>
					<MODS:titleInfo ID="MODSMD_PRINT_TI1" xml:lang="en">
						<MODS:title>Oxford Observer</MODS:title>
						<MODS:partNumber>VI</MODS:partNumber>
					</MODS:titleInfo>
					<MODS:language>
						<MODS:languageTerm type="code" authority="rfc3066">en</MODS:languageTerm>
					</MODS:language>
					<MODS:originInfo>
						<MODS:dateIssued encoding="w3cdtf" point="start" keyDate="yes" qualifier="approximate">1895-03-23</MODS:dateIssued>
					</MODS:originInfo>
					<MODS:identifier type="local">OO_18950323</MODS:identifier>
				</MODS:mods>
			</xmlData>
		</mdWrap>
	</dmdSec>
	<dmdSec ID="MODSMD_ELEC">
		<mdWrap MIMETYPE="text/xml" MDTYPE="MODS" LABEL="Bibliographic meta-data of the electronic version">
			<xmlData>
				<MODS:mods>
					<MODS:originInfo>
						<MODS:dateCreated point="start" keyDate="yes" qualifier="approximate">2009-01-23</MODS:dateCreated>
						<MODS:publisher>CCS Content Conversion Specialists GmbH</MODS:publisher>
					</MODS:originInfo>
					<MODS:titleInfo ID="MODSMD_ELEC_TI1" xml:lang="en">
						<MODS:title>Oxford Observer</MODS:title>
						<MODS:partNumber>VI</MODS:partNumber>
					</MODS:titleInfo>
					<MODS:language>
						<MODS:languageTerm type="code" authority="rfc3066">en</MODS:languageTerm>
					</MODS:language>
					<MODS:identifier type="local">OO_18950323</MODS:identifier>
				</MODS:mods>
			</xmlData>
		</mdWrap>
	</dmdSec>
	<dmdSec ID="MODSMD_ISSUE1">
		<mdWrap MIMETYPE="text/xml" MDTYPE="MODS" LABEL="Bibliographic meta-data of Issue">
			<xmlData>
				<MODS:mods>
					<MODS:titleInfo ID="MODSMD_ISSUE1_TI1" xml:lang="en">
						<MODS:title>Oxford Observer</MODS:title>
					</MODS:titleInfo>
					<MODS:language>
						<MODS:languageTerm type="code" authority="rfc3066">en</MODS:languageTerm>
					</MODS:language>
					<MODS:originInfo>
						<MODS:dateIssued encoding="w3cdtf" point="start" keyDate="yes" qualifier="approximate">1895-03-23</MODS:dateIssued>
					</MODS:originInfo>
					<MODS:identifier type="local">OO_18950323</MODS:identifier>
					<MODS:relatedItem ID="MODSMD_ISSUE1_RI1" type="host">
						<MODS:identifier type="local">VI</MODS:identifier>
					</MODS:relatedItem>
				</MODS:mods>
			</xmlData>
		</mdWrap>
	</dmdSec>
	<dmdSec ID="MODSMD_ARTICLE1">
		<mdWrap MIMETYPE="text/xml" MDTYPE="MODS" LABEL="Bibliographic meta-data of article">
			<xmlData>
				<MODS:mods>
					<MODS:titleInfo ID="MODSMD_ARTICLE1_TI1" xml:lang="en">
						<MODS:nonSort>The</MODS:nonSort>
						<MODS:title>Oxford Observer.  PUBLISHED WEEKLY. SATURDAY MARCH 23rd, 1895.</MODS:title>
					</MODS:titleInfo>
					<MODS:language>
						<MODS:languageTerm type="code" authority="rfc3066">en</MODS:languageTerm>
					</MODS:language>
				</MODS:mods>
			</xmlData>
		</mdWrap>
	</dmdSec>
	<dmdSec ID="MODSMD_ARTICLE2">
		<mdWrap MIMETYPE="text/xml" MDTYPE="MODS" LABEL="Bibliographic meta-data of article">
			<xmlData>
				<MODS:mods>
					<MODS:titleInfo ID="MODSMD_ARTICLE2_TI2" xml:lang="en">
						<MODS:title>PHILOSOPHIC MATERIALISM.</MODS:title>
					</MODS:titleInfo>
					<MODS:language>
						<MODS:languageTerm type="code" authority="rfc3066">en</MODS:languageTerm>
					</MODS:language>
				</MODS:mods>
			</xmlData>
		</mdWrap>
	</dmdSec>
	<dmdSec ID="MODSMD_ARTICLE3">
		<mdWrap MIMETYPE="text/xml" MDTYPE="MODS" LABEL="Bibliographic meta-data of article">
			<xmlData>
				<MODS:mods>
					<MODS:titleInfo ID="MODSMD_ARTICLE3_TI3" xml:lang="en">
						<MODS:title>OXFORD DISTRICT RACES.</MODS:title>
					</MODS:titleInfo>
					<MODS:language>
						<MODS:languageTerm type="code" authority="rfc3066">en</MODS:languageTerm>
					</MODS:language>
				</MODS:mods>
			</xmlData>
		</mdWrap>
	</dmdSec>
	<dmdSec ID="MODSMD_SECTION1">
		<mdWrap MIMETYPE="text/xml" MDTYPE="MODS" LABEL="Bibliographic meta-data of section">
			<xmlData>
				<MODS:mods>
					<MODS:titleInfo ID="MODSMD_SECTION1_TI1" xml:lang="en">
						<MODS:title>CORRESPONDENCE.</MODS:title>
					</MODS:titleInfo>
					<MODS:language>
						<MODS:languageTerm type="code" authority="rfc3066">en</MODS:languageTerm>
					</MODS:language>
				</MODS:mods>
			</xmlData>
		</mdWrap>
	</dmdSec>
	<dmdSec ID="MODSMD_ARTICLE4">
		<mdWrap MIMETYPE="text/xml" MDTYPE="MODS" LABEL="Bibliographic meta-data of article">
			<xmlData>
				<MODS:mods>
					<MODS:titleInfo ID="MODSMD_ARTICLE4_TI4" xml:lang="en">
						<MODS:title>THE ATTRACTIONS OF OXFORD.</MODS:title>
					</MODS:titleInfo>
					<MODS:language>
						<MODS:languageTerm type="code" authority="rfc3066">en</MODS:languageTerm>
					</MODS:language>
				</MODS:mods>
			</xmlData>
		</mdWrap>
	</dmdSec>
	<dmdSec ID="MODSMD_ARTICLE5">
		<mdWrap MIMETYPE="text/xml" MDTYPE="MODS" LABEL="Bibliographic meta-data of article">
			<xmlData>
				<MODS:mods>
					<MODS:titleInfo ID="MODSMD_ARTICLE5_TI5" xml:lang="en">
						<MODS:title>SALVATION ARMY.</MODS:title>
					</MODS:titleInfo>
					<MODS:language>
						<MODS:languageTerm type="code" authority="rfc3066">en</MODS:languageTerm>
					</MODS:language>
				</MODS:mods>
			</xmlData>
		</mdWrap>
	</dmdSec>
	<dmdSec ID="MODSMD_ARTICLE6">
		<mdWrap MIMETYPE="text/xml" MDTYPE="MODS" LABEL="Bibliographic meta-data of article">
			<xmlData>
				<MODS:mods>
					<MODS:titleInfo ID="MODSMD_ARTICLE6_TI6" xml:lang="en">
						<MODS:title>"WHY DO THE BEST MEN LEAVE THE CHURCH"?</MODS:title>
					</MODS:titleInfo>
					<MODS:language>
						<MODS:languageTerm type="code" authority="rfc3066">en</MODS:languageTerm>
					</MODS:language>
				</MODS:mods>
			</xmlData>
		</mdWrap>
	</dmdSec>
	<dmdSec ID="MODSMD_ARTICLE7">
		<mdWrap MIMETYPE="text/xml" MDTYPE="MODS" LABEL="Bibliographic meta-data of article">
			<xmlData>
				<MODS:mods>
					<MODS:titleInfo ID="MODSMD_ARTICLE7_TI7" xml:lang="en">
						<MODS:nonSort>A</MODS:nonSort>
						<MODS:title>STRANGE PHENOMENA.</MODS:title>
					</MODS:titleInfo>
					<MODS:language>
						<MODS:languageTerm type="code" authority="rfc3066">en</MODS:languageTerm>
					</MODS:language>
				</MODS:mods>
			</xmlData>
		</mdWrap>
	</dmdSec>
	<dmdSec ID="MODSMD_ARTICLE8">
		<mdWrap MIMETYPE="text/xml" MDTYPE="MODS" LABEL="Bibliographic meta-data of article">
			<xmlData>
				<MODS:mods>
					<MODS:titleInfo ID="MODSMD_ARTICLE8_TI8" xml:lang="en">
						<MODS:title>ACCIDENTS.</MODS:title>
					</MODS:titleInfo>
					<MODS:language>
						<MODS:languageTerm type="code" authority="rfc3066">en</MODS:languageTerm>
					</MODS:language>
				</MODS:mods>
			</xmlData>
		</mdWrap>
	</dmdSec>
	<dmdSec ID="MODSMD_ARTICLE9">
		<mdWrap MIMETYPE="text/xml" MDTYPE="MODS" LABEL="Bibliographic meta-data of article">
			<xmlData>
				<MODS:mods>
					<MODS:titleInfo ID="MODSMD_ARTICLE9_TI9" xml:lang="en">
						<MODS:title>NOTES AND NOTIONS.</MODS:title>
					</MODS:titleInfo>
					<MODS:language>
						<MODS:languageTerm type="code" authority="rfc3066">en</MODS:languageTerm>
					</MODS:language>
				</MODS:mods>
			</xmlData>
		</mdWrap>
	</dmdSec>
	<dmdSec ID="MODSMD_ARTICLE10">
		<mdWrap MIMETYPE="text/xml" MDTYPE="MODS" LABEL="Bibliographic meta-data of article">
			<xmlData>
				<MODS:mods>
					<MODS:titleInfo ID="MODSMD_ARTICLE10_TI10" xml:lang="en">
						<MODS:nonSort>A</MODS:nonSort>
						<MODS:title>SUPERIOR KIND OF COW.</MODS:title>
					</MODS:titleInfo>
					<MODS:language>
						<MODS:languageTerm type="code" authority="rfc3066">en</MODS:languageTerm>
					</MODS:language>
				</MODS:mods>
			</xmlData>
		</mdWrap>
	</dmdSec>
	<dmdSec ID="MODSMD_ARTICLE11">
		<mdWrap MIMETYPE="text/xml" MDTYPE="MODS" LABEL="Bibliographic meta-data of article">
			<xmlData>
				<MODS:mods>
					<MODS:titleInfo ID="MODSMD_ARTICLE11_TI11" xml:lang="en">
						<MODS:title>COOLGARDIE.</MODS:title>
					</MODS:titleInfo>
					<MODS:language>
						<MODS:languageTerm type="code" authority="rfc3066">en</MODS:languageTerm>
					</MODS:language>
				</MODS:mods>
			</xmlData>
		</mdWrap>
	</dmdSec>
	<dmdSec ID="MODSMD_ARTICLE12">
		<mdWrap MIMETYPE="text/xml" MDTYPE="MODS" LABEL="Bibliographic meta-data of article">
			<xmlData>
				<MODS:mods>
					<MODS:titleInfo ID="MODSMD_ARTICLE12_TI12" xml:lang="en">
						<MODS:title>LOCAL AND GENERAL</MODS:title>
					</MODS:titleInfo>
					<MODS:language>
						<MODS:languageTerm type="code" authority="rfc3066">en</MODS:languageTerm>
					</MODS:language>
				</MODS:mods>
			</xmlData>
		</mdWrap>
	</dmdSec>
	<dmdSec ID="MODSMD_ARTICLE13">
		<mdWrap MIMETYPE="text/xml" MDTYPE="MODS" LABEL="Bibliographic meta-data of article">
			<xmlData>
				<MODS:mods>
					<MODS:titleInfo ID="MODSMD_ARTICLE13_TI13" xml:lang="en">
						<MODS:title>PHOTOGRAPHY OF STARS.</MODS:title>
					</MODS:titleInfo>
					<MODS:language>
						<MODS:languageTerm type="code" authority="rfc3066">en</MODS:languageTerm>
					</MODS:language>
				</MODS:mods>
			</xmlData>
		</mdWrap>
	</dmdSec>
	<dmdSec ID="MODSMD_ARTICLE14">
		<mdWrap MIMETYPE="text/xml" MDTYPE="MODS" LABEL="Bibliographic meta-data of article">
			<xmlData>
				<MODS:mods>
					<MODS:titleInfo ID="MODSMD_ARTICLE14_TI14" xml:lang="en">
						<MODS:title>OXFORD LIBRARY AND READING ROOM.</MODS:title>
					</MODS:titleInfo>
					<MODS:language>
						<MODS:languageTerm type="code" authority="rfc3066">en</MODS:languageTerm>
					</MODS:language>
				</MODS:mods>
			</xmlData>
		</mdWrap>
	</dmdSec>
	<dmdSec ID="MODSMD_ARTICLE15">
		<mdWrap MIMETYPE="text/xml" MDTYPE="MODS" LABEL="Bibliographic meta-data of article">
			<xmlData>
				<MODS:mods>
					<MODS:titleInfo ID="MODSMD_ARTICLE15_TI15" xml:lang="en">
						<MODS:title>THE CHEAP MONEY SCHEME.</MODS:title>
					</MODS:titleInfo>
					<MODS:language>
						<MODS:languageTerm type="code" authority="rfc3066">en</MODS:languageTerm>
					</MODS:language>
				</MODS:mods>
			</xmlData>
		</mdWrap>
	</dmdSec>
	<dmdSec ID="MODSMD_SECTION2">
		<mdWrap MIMETYPE="text/xml" MDTYPE="MODS" LABEL="Bibliographic meta-data of section">
			<xmlData>
				<MODS:mods>
					<MODS:language>
						<MODS:languageTerm type="code" authority="rfc3066">en</MODS:languageTerm>
					</MODS:language>
				</MODS:mods>
			</xmlData>
		</mdWrap>
	</dmdSec>
	<amdSec ID="IMGPARAM00001">
		<techMD ID="IMGPARAM00001TECHMD">
			<mdWrap MDTYPE="NISOIMG">
				<xmlData>
					<mix:mix>
						<mix:BasicImageParameters>
							<mix:Format>
								<mix:MIMEType>image/tiff</mix:MIMEType>
								<mix:ByteOrder>little-endian</mix:ByteOrder>
								<mix:Compression>
									<mix:CompressionScheme>4</mix:CompressionScheme>
								</mix:Compression>
								<mix:PhotometricInterpretation>
									<mix:ColorSpace>1</mix:ColorSpace>
								</mix:PhotometricInterpretation>
							</mix:Format>
							<mix:File>
								<mix:ImageIdentifier imageIdentifierLocation="//nasserver-9/impdata$/OUT/NZ/OO/OO_18950323/MM_01">0001.tif</mix:ImageIdentifier>
								<mix:FileSize>402279</mix:FileSize>
								<mix:Orientation>1</mix:Orientation>
								<mix:DisplayOrientation>1</mix:DisplayOrientation>
							</mix:File>
						</mix:BasicImageParameters>
						<mix:ImageCreation>
							<mix:SourceType>Newspaper</mix:SourceType>
							<mix:SourceID></mix:SourceID>
							<mix:ImageProducer></mix:ImageProducer>
							<mix:Host>
								<mix:HostComputer>DOCPC-09</mix:HostComputer>
								<mix:OperatingSystem>windows</mix:OperatingSystem>
								<mix:OSVersion>5.1 Service Pack 2</mix:OSVersion>
							</mix:Host>
							<mix:DeviceSource></mix:DeviceSource>
							<mix:ScanningSystemCapture>
								<mix:ScanningSystemHardware>
									<mix:ScannerManufacturer></mix:ScannerManufacturer>
									<mix:ScannerModel>
										<mix:ScannerModelName></mix:ScannerModelName>
										<mix:ScannerModelNumber></mix:ScannerModelNumber>
										<mix:ScannerModelSerialNo></mix:ScannerModelSerialNo>
									</mix:ScannerModel>
								</mix:ScanningSystemHardware>
								<mix:ScanningSystemSoftware>
									<mix:ScanningSoftware>CCS docWORKS</mix:ScanningSoftware>
									<mix:ScanningSoftwareVersionNo></mix:ScanningSoftwareVersionNo>
								</mix:ScanningSystemSoftware>
								<mix:ScannerCaptureSettings>
									<mix:PixelSize>0.0635000</mix:PixelSize>
									<mix:PhysScanResolution>
										<mix:XphysScanResolution>400</mix:XphysScanResolution>
										<mix:YphysScanResolution>400</mix:YphysScanResolution>
									</mix:PhysScanResolution>
								</mix:ScannerCaptureSettings>
							</mix:ScanningSystemCapture>
						</mix:ImageCreation>
						<mix:ImagingPerformanceAssessment>
							<mix:SpatialMetrics>
								<mix:ImageWidth>5384</mix:ImageWidth>
								<mix:ImageLength>6880</mix:ImageLength>
							</mix:SpatialMetrics>
							<mix:Energetics>
								<mix:BitsPerSample>1</mix:BitsPerSample>
								<mix:SamplesPerPixel>1</mix:SamplesPerPixel>
							</mix:Energetics>
						</mix:ImagingPerformanceAssessment>
						<mix:ChangeHistory>
							<mix:ImageProcessing>
								<mix:SourceData>./NZ_5/OO/1895/03/23/00100.TIF</mix:SourceData>
							</mix:ImageProcessing>
						</mix:ChangeHistory>
					</mix:mix>
				</xmlData>
			</mdWrap>
		</techMD>
	</amdSec>
	<amdSec ID="IMGPARAM00002">
		<techMD ID="IMGPARAM00002TECHMD">
			<mdWrap MDTYPE="NISOIMG">
				<xmlData>
					<mix:mix>
						<mix:BasicImageParameters>
							<mix:Format>
								<mix:MIMEType>image/tiff</mix:MIMEType>
								<mix:ByteOrder>little-endian</mix:ByteOrder>
								<mix:Compression>
									<mix:CompressionScheme>4</mix:CompressionScheme>
								</mix:Compression>
								<mix:PhotometricInterpretation>
									<mix:ColorSpace>1</mix:ColorSpace>
								</mix:PhotometricInterpretation>
							</mix:Format>
							<mix:File>
								<mix:ImageIdentifier imageIdentifierLocation="//nasserver-9/impdata$/OUT/NZ/OO/OO_18950323/MM_01">0002.tif</mix:ImageIdentifier>
								<mix:FileSize>553238</mix:FileSize>
								<mix:Orientation>1</mix:Orientation>
								<mix:DisplayOrientation>1</mix:DisplayOrientation>
							</mix:File>
						</mix:BasicImageParameters>
						<mix:ImageCreation>
							<mix:SourceType>Newspaper</mix:SourceType>
							<mix:SourceID></mix:SourceID>
							<mix:ImageProducer></mix:ImageProducer>
							<mix:Host>
								<mix:HostComputer>DOCPC-09</mix:HostComputer>
								<mix:OperatingSystem>windows</mix:OperatingSystem>
								<mix:OSVersion>5.1 Service Pack 2</mix:OSVersion>
							</mix:Host>
							<mix:DeviceSource></mix:DeviceSource>
							<mix:ScanningSystemCapture>
								<mix:ScanningSystemHardware>
									<mix:ScannerManufacturer></mix:ScannerManufacturer>
									<mix:ScannerModel>
										<mix:ScannerModelName></mix:ScannerModelName>
										<mix:ScannerModelNumber></mix:ScannerModelNumber>
										<mix:ScannerModelSerialNo></mix:ScannerModelSerialNo>
									</mix:ScannerModel>
								</mix:ScanningSystemHardware>
								<mix:ScanningSystemSoftware>
									<mix:ScanningSoftware>CCS docWORKS</mix:ScanningSoftware>
									<mix:ScanningSoftwareVersionNo></mix:ScanningSoftwareVersionNo>
								</mix:ScanningSystemSoftware>
								<mix:ScannerCaptureSettings>
									<mix:PixelSize>0.0635000</mix:PixelSize>
									<mix:PhysScanResolution>
										<mix:XphysScanResolution>400</mix:XphysScanResolution>
										<mix:YphysScanResolution>400</mix:YphysScanResolution>
									</mix:PhysScanResolution>
								</mix:ScannerCaptureSettings>
							</mix:ScanningSystemCapture>
						</mix:ImageCreation>
						<mix:ImagingPerformanceAssessment>
							<mix:SpatialMetrics>
								<mix:ImageWidth>5512</mix:ImageWidth>
								<mix:ImageLength>7213</mix:ImageLength>
							</mix:SpatialMetrics>
							<mix:Energetics>
								<mix:BitsPerSample>1</mix:BitsPerSample>
								<mix:SamplesPerPixel>1</mix:SamplesPerPixel>
							</mix:Energetics>
						</mix:ImagingPerformanceAssessment>
						<mix:ChangeHistory>
							<mix:ImageProcessing>
								<mix:SourceData>./NZ_5/OO/1895/03/23/00200.TIF</mix:SourceData>
							</mix:ImageProcessing>
						</mix:ChangeHistory>
					</mix:mix>
				</xmlData>
			</mdWrap>
		</techMD>
	</amdSec>
	<amdSec ID="IMGPARAM00003">
		<techMD ID="IMGPARAM00003TECHMD">
			<mdWrap MDTYPE="NISOIMG">
				<xmlData>
					<mix:mix>
						<mix:BasicImageParameters>
							<mix:Format>
								<mix:MIMEType>image/tiff</mix:MIMEType>
								<mix:ByteOrder>little-endian</mix:ByteOrder>
								<mix:Compression>
									<mix:CompressionScheme>4</mix:CompressionScheme>
								</mix:Compression>
								<mix:PhotometricInterpretation>
									<mix:ColorSpace>1</mix:ColorSpace>
								</mix:PhotometricInterpretation>
							</mix:Format>
							<mix:File>
								<mix:ImageIdentifier imageIdentifierLocation="//nasserver-9/impdata$/OUT/NZ/OO/OO_18950323/MM_01">0003.tif</mix:ImageIdentifier>
								<mix:FileSize>616062</mix:FileSize>
								<mix:Orientation>1</mix:Orientation>
								<mix:DisplayOrientation>1</mix:DisplayOrientation>
							</mix:File>
						</mix:BasicImageParameters>
						<mix:ImageCreation>
							<mix:SourceType>Newspaper</mix:SourceType>
							<mix:SourceID></mix:SourceID>
							<mix:ImageProducer></mix:ImageProducer>
							<mix:Host>
								<mix:HostComputer>DOCPC-09</mix:HostComputer>
								<mix:OperatingSystem>windows</mix:OperatingSystem>
								<mix:OSVersion>5.1 Service Pack 2</mix:OSVersion>
							</mix:Host>
							<mix:DeviceSource></mix:DeviceSource>
							<mix:ScanningSystemCapture>
								<mix:ScanningSystemHardware>
									<mix:ScannerManufacturer></mix:ScannerManufacturer>
									<mix:ScannerModel>
										<mix:ScannerModelName></mix:ScannerModelName>
										<mix:ScannerModelNumber></mix:ScannerModelNumber>
										<mix:ScannerModelSerialNo></mix:ScannerModelSerialNo>
									</mix:ScannerModel>
								</mix:ScanningSystemHardware>
								<mix:ScanningSystemSoftware>
									<mix:ScanningSoftware>CCS docWORKS</mix:ScanningSoftware>
									<mix:ScanningSoftwareVersionNo></mix:ScanningSoftwareVersionNo>
								</mix:ScanningSystemSoftware>
								<mix:ScannerCaptureSettings>
									<mix:PixelSize>0.0635000</mix:PixelSize>
									<mix:PhysScanResolution>
										<mix:XphysScanResolution>400</mix:XphysScanResolution>
										<mix:YphysScanResolution>400</mix:YphysScanResolution>
									</mix:PhysScanResolution>
								</mix:ScannerCaptureSettings>
							</mix:ScanningSystemCapture>
						</mix:ImageCreation>
						<mix:ImagingPerformanceAssessment>
							<mix:SpatialMetrics>
								<mix:ImageWidth>5512</mix:ImageWidth>
								<mix:ImageLength>7213</mix:ImageLength>
							</mix:SpatialMetrics>
							<mix:Energetics>
								<mix:BitsPerSample>1</mix:BitsPerSample>
								<mix:SamplesPerPixel>1</mix:SamplesPerPixel>
							</mix:Energetics>
						</mix:ImagingPerformanceAssessment>
						<mix:ChangeHistory>
							<mix:ImageProcessing>
								<mix:SourceData>./NZ_5/OO/1895/03/23/00300.TIF</mix:SourceData>
							</mix:ImageProcessing>
						</mix:ChangeHistory>
					</mix:mix>
				</xmlData>
			</mdWrap>
		</techMD>
	</amdSec>
	<amdSec ID="IMGPARAM00004">
		<techMD ID="IMGPARAM00004TECHMD">
			<mdWrap MDTYPE="NISOIMG">
				<xmlData>
					<mix:mix>
						<mix:BasicImageParameters>
							<mix:Format>
								<mix:MIMEType>image/tiff</mix:MIMEType>
								<mix:ByteOrder>little-endian</mix:ByteOrder>
								<mix:Compression>
									<mix:CompressionScheme>4</mix:CompressionScheme>
								</mix:Compression>
								<mix:PhotometricInterpretation>
									<mix:ColorSpace>1</mix:ColorSpace>
								</mix:PhotometricInterpretation>
							</mix:Format>
							<mix:File>
								<mix:ImageIdentifier imageIdentifierLocation="//nasserver-9/impdata$/OUT/NZ/OO/OO_18950323/MM_01">0004.tif</mix:ImageIdentifier>
								<mix:FileSize>472067</mix:FileSize>
								<mix:Orientation>1</mix:Orientation>
								<mix:DisplayOrientation>1</mix:DisplayOrientation>
							</mix:File>
						</mix:BasicImageParameters>
						<mix:ImageCreation>
							<mix:SourceType>Newspaper</mix:SourceType>
							<mix:SourceID></mix:SourceID>
							<mix:ImageProducer></mix:ImageProducer>
							<mix:Host>
								<mix:HostComputer>DOCPC-09</mix:HostComputer>
								<mix:OperatingSystem>windows</mix:OperatingSystem>
								<mix:OSVersion>5.1 Service Pack 2</mix:OSVersion>
							</mix:Host>
							<mix:DeviceSource></mix:DeviceSource>
							<mix:ScanningSystemCapture>
								<mix:ScanningSystemHardware>
									<mix:ScannerManufacturer></mix:ScannerManufacturer>
									<mix:ScannerModel>
										<mix:ScannerModelName></mix:ScannerModelName>
										<mix:ScannerModelNumber></mix:ScannerModelNumber>
										<mix:ScannerModelSerialNo></mix:ScannerModelSerialNo>
									</mix:ScannerModel>
								</mix:ScanningSystemHardware>
								<mix:ScanningSystemSoftware>
									<mix:ScanningSoftware>CCS docWORKS</mix:ScanningSoftware>
									<mix:ScanningSoftwareVersionNo></mix:ScanningSoftwareVersionNo>
								</mix:ScanningSystemSoftware>
								<mix:ScannerCaptureSettings>
									<mix:PixelSize>0.0635000</mix:PixelSize>
									<mix:PhysScanResolution>
										<mix:XphysScanResolution>400</mix:XphysScanResolution>
										<mix:YphysScanResolution>400</mix:YphysScanResolution>
									</mix:PhysScanResolution>
								</mix:ScannerCaptureSettings>
							</mix:ScanningSystemCapture>
						</mix:ImageCreation>
						<mix:ImagingPerformanceAssessment>
							<mix:SpatialMetrics>
								<mix:ImageWidth>5477</mix:ImageWidth>
								<mix:ImageLength>7027</mix:ImageLength>
							</mix:SpatialMetrics>
							<mix:Energetics>
								<mix:BitsPerSample>1</mix:BitsPerSample>
								<mix:SamplesPerPixel>1</mix:SamplesPerPixel>
							</mix:Energetics>
						</mix:ImagingPerformanceAssessment>
						<mix:ChangeHistory>
							<mix:ImageProcessing>
								<mix:SourceData>./NZ_5/OO/1895/03/23/00400.TIF</mix:SourceData>
							</mix:ImageProcessing>
						</mix:ChangeHistory>
					</mix:mix>
				</xmlData>
			</mdWrap>
		</techMD>
	</amdSec>
	<fileSec>
		<fileGrp ID="IMGGRP" USE="Images">
			<file ID="IMG00001" CREATED="2009-01-23T18:36:46" ADMID="IMGPARAM00001" MIMETYPE="image/tif" SEQ="1" CHECKSUM="302ee62a84242c6fdf0c9cc1ee64c24f" CHECKSUMTYPE="MD5" SIZE="402279">
				<FLocat LOCTYPE="URL" xlink:href="file://./0001.tif"/>
			</file>
			<file ID="IMG00002" CREATED="2009-01-23T18:36:48" ADMID="IMGPARAM00002" MIMETYPE="image/tif" SEQ="2" CHECKSUM="da2ae94e82012baee787f1571c7b2f93" CHECKSUMTYPE="MD5" SIZE="553238">
				<FLocat LOCTYPE="URL" xlink:href="file://./0002.tif"/>
			</file>
			<file ID="IMG00003" CREATED="2009-01-23T18:36:50" ADMID="IMGPARAM00003" MIMETYPE="image/tif" SEQ="3" CHECKSUM="4f9b1df6646e3c5344f9876cb0f64ee9" CHECKSUMTYPE="MD5" SIZE="616062">
				<FLocat LOCTYPE="URL" xlink:href="file://./0003.tif"/>
			</file>
			<file ID="IMG00004" CREATED="2009-01-23T18:36:52" ADMID="IMGPARAM00004" MIMETYPE="image/tif" SEQ="4" CHECKSUM="3a5bada061ceeffe3a2bc5078c33934a" CHECKSUMTYPE="MD5" SIZE="472067">
				<FLocat LOCTYPE="URL" xlink:href="file://./0004.tif"/>
			</file>
		</fileGrp>
		<fileGrp ID="ALTOGRP" USE="Text">
			<file ID="ALTO0001" CREATED="2009-01-23T18:36:53" MIMETYPE="text/xml" CHECKSUM="720199d61219edbb08f69806e093bf5b" CHECKSUMTYPE="MD5" SIZE="356418">
				<FLocat LOCTYPE="URL" xlink:href="file://./0001.xml"/>
			</file>
			<file ID="ALTO0002" CREATED="2009-01-23T18:36:54" MIMETYPE="text/xml" CHECKSUM="bb10356454f2654ac1cf23c06bad0b15" CHECKSUMTYPE="MD5" SIZE="514618">
				<FLocat LOCTYPE="URL" xlink:href="file://./0002.xml"/>
			</file>
			<file ID="ALTO0003" CREATED="2009-01-23T18:36:55" MIMETYPE="text/xml" CHECKSUM="910556b5c6c39698335aa9c4b2e1119f" CHECKSUMTYPE="MD5" SIZE="725300">
				<FLocat LOCTYPE="URL" xlink:href="file://./0003.xml"/>
			</file>
			<file ID="ALTO0004" CREATED="2009-01-23T18:36:56" MIMETYPE="text/xml" CHECKSUM="2814aefdd02e7e042e7b40c95e080abb" CHECKSUMTYPE="MD5" SIZE="363513">
				<FLocat LOCTYPE="URL" xlink:href="file://./0004.xml"/>
			</file>
		</fileGrp>
	</fileSec>
	<structMap LABEL="Physical Structure" TYPE="PHYSICAL">
		<div ID="DIVP1" DMDID="MODSMD_ELEC MODSMD_PRINT" LABEL="Oxford Observer" TYPE="Newspaper">
			<div ID="DIVP2" ORDER="1" ORDERLABEL="1" TYPE="PAGE">
				<fptr>
					<par>
						<area FILEID="IMG00001"/>
						<area FILEID="ALTO0001" BETYPE="IDREF" BEGIN="P1"/>
					</par>
				</fptr>
			</div>
			<div ID="DIVP3" ORDER="2" ORDERLABEL="2" TYPE="PAGE">
				<fptr>
					<par>
						<area FILEID="IMG00002"/>
						<area FILEID="ALTO0002" BETYPE="IDREF" BEGIN="P2"/>
					</par>
				</fptr>
			</div>
			<div ID="DIVP4" ORDER="3" ORDERLABEL="3" TYPE="PAGE">
				<fptr>
					<par>
						<area FILEID="IMG00003"/>
						<area FILEID="ALTO0003" BETYPE="IDREF" BEGIN="P3"/>
					</par>
				</fptr>
			</div>
			<div ID="DIVP5" ORDER="4" ORDERLABEL="4" TYPE="PAGE">
				<fptr>
					<par>
						<area FILEID="IMG00004"/>
						<area FILEID="ALTO0004" BETYPE="IDREF" BEGIN="P4"/>
					</par>
				</fptr>
			</div>
		</div>
	</structMap>
	<structMap LABEL="Logical Structure" TYPE="LOGICAL">
		<div ID="DIVL1" TYPE="Newspaper" LABEL="Oxford Observer no.  1895-03-23">
			<div ID="DIVL2" TYPE="VOLUME" DMDID="MODSMD_PRINT MODSMD_ELEC" LABEL="Oxford Observer no.  1895-03-23">
				<div ID="DIVL3" TYPE="ISSUE" DMDID="MODSMD_ISSUE1" LABEL="Oxford Observer no.  1895-03-23">
					<div ID="DIVL4" TYPE="TITLE_SECTION">
						<div ID="DIVL5" TYPE="HEADLINE" ORDER="1">
							<fptr>
								<area BETYPE="IDREF" FILEID="ALTO0001" BEGIN="P1_TB00001"/>
							</fptr>
						</div>
						<div ID="DIVL6" TYPE="TEXTBLOCK" ORDER="2">
							<fptr>
								<area BETYPE="IDREF" FILEID="ALTO0001" BEGIN="P1_TB00002"/>
							</fptr>
						</div>
						<div ID="DIVL7" TYPE="TEXTBLOCK" ORDER="3">
							<fptr>
								<area BETYPE="IDREF" FILEID="ALTO0001" BEGIN="P1_TB00003"/>
							</fptr>
						</div>
						<div ID="DIVL8" TYPE="TEXTBLOCK" ORDER="4">
							<fptr>
								<area BETYPE="IDREF" FILEID="ALTO0001" BEGIN="P1_TB00004"/>
							</fptr>
						</div>
						<div ID="DIVL9" TYPE="TEXTBLOCK" ORDER="5">
							<fptr>
								<area BETYPE="IDREF" FILEID="ALTO0001" BEGIN="P1_TB00005"/>
							</fptr>
						</div>
						<div ID="DIVL10" TYPE="TEXTBLOCK" ORDER="6">
							<fptr>
								<area BETYPE="IDREF" FILEID="ALTO0001" BEGIN="P1_TB00006"/>
							</fptr>
						</div>
					</div>
					<div ID="DIVL11" TYPE="CONTENT">
						<div ID="DIVL12" TYPE="ARTICLE" DMDID="MODSMD_ARTICLE1" LABEL="The Oxford Observer.  PUBLISHED WEEKLY. SATURDAY MARCH 23rd, 1895.">
							<div ID="DIVL13" TYPE="HEADING">
								<div ID="DIVL14" TYPE="TITLE">
									<fptr>
										<area BETYPE="IDREF" FILEID="ALTO0002" BEGIN="P2_TB00001"/>
									</fptr>
								</div>
							</div>
							<div ID="DIVL15" TYPE="BODY">
								<div ID="DIVL16" TYPE="BODY_CONTENT">
									<div ID="DIVL17" TYPE="PARAGRAPH" ORDER="1">
										<div ID="DIVL18" TYPE="TEXT">
											<fptr>
												<seq>
													<area BETYPE="IDREF" FILEID="ALTO0002" BEGIN="P2_TB00002"/>
													<area BETYPE="IDREF" FILEID="ALTO0002" BEGIN="P2_TB00003"/>
												</seq>
											</fptr>
										</div>
									</div>
								</div>
							</div>
						</div>
						<div ID="DIVL19" TYPE="ARTICLE" DMDID="MODSMD_ARTICLE2" LABEL="PHILOSOPHIC MATERIALISM.">
							<div ID="DIVL20" TYPE="HEADING">
								<div ID="DIVL21" TYPE="TITLE">
									<fptr>
										<area BETYPE="IDREF" FILEID="ALTO0002" BEGIN="P2_TB00004"/>
									</fptr>
								</div>
							</div>
							<div ID="DIVL22" TYPE="BODY">
								<div ID="DIVL23" TYPE="BODY_CONTENT">
									<div ID="DIVL24" TYPE="PARAGRAPH" ORDER="1">
										<div ID="DIVL25" TYPE="TEXT">
											<fptr>
												<area BETYPE="IDREF" FILEID="ALTO0002" BEGIN="P2_TB00005"/>
											</fptr>
										</div>
									</div>
									<div ID="DIVL26" TYPE="PARAGRAPH" ORDER="2">
										<div ID="DIVL27" TYPE="TEXT">
											<fptr>
												<area BETYPE="IDREF" FILEID="ALTO0003" BEGIN="P3_TB00001"/>
											</fptr>
										</div>
									</div>
								</div>
							</div>
						</div>
						<div ID="DIVL28" TYPE="ARTICLE" DMDID="MODSMD_ARTICLE3" LABEL="OXFORD DISTRICT RACES.">
							<div ID="DIVL29" TYPE="HEADING">
								<div ID="DIVL30" TYPE="TITLE">
									<fptr>
										<area BETYPE="IDREF" FILEID="ALTO0003" BEGIN="P3_TB00002"/>
									</fptr>
								</div>
							</div>
							<div ID="DIVL31" TYPE="BODY">
								<div ID="DIVL32" TYPE="BODY_CONTENT">
									<div ID="DIVL33" TYPE="PARAGRAPH" ORDER="1">
										<div ID="DIVL34" TYPE="TEXT">
											<fptr>
												<area BETYPE="IDREF" FILEID="ALTO0003" BEGIN="P3_TB00003"/>
											</fptr>
										</div>
									</div>
									<div ID="DIVL35" TYPE="PARAGRAPH" ORDER="2">
										<div ID="DIVL36" TYPE="TEXT">
											<fptr>
												<seq>
													<area BETYPE="IDREF" FILEID="ALTO0003" BEGIN="P3_TB00004"/>
													<area BETYPE="IDREF" FILEID="ALTO0003" BEGIN="P3_TB00005"/>
												</seq>
											</fptr>
										</div>
									</div>
								</div>
							</div>
						</div>
						<div ID="DIVL37" TYPE="SECTION" DMDID="MODSMD_SECTION1" LABEL="CORRESPONDENCE.">
							<div ID="DIVL38" TYPE="HEADING">
								<div ID="DIVL39" TYPE="TITLE">
									<fptr>
										<area BETYPE="IDREF" FILEID="ALTO0003" BEGIN="P3_TB00006"/>
									</fptr>
								</div>
							</div>
							<div ID="DIVL40" TYPE="BODY">
								<div ID="DIVL41" TYPE="BODY_CONTENT">
									<div ID="DIVL42" TYPE="PARAGRAPH" ORDER="1">
										<div ID="DIVL43" TYPE="TEXT">
											<fptr>
												<area BETYPE="IDREF" FILEID="ALTO0003" BEGIN="P3_TB00007"/>
											</fptr>
										</div>
									</div>
									<div ID="DIVL44" TYPE="PARAGRAPH" ORDER="2">
										<div ID="DIVL45" TYPE="TEXT">
											<fptr>
												<area BETYPE="IDREF" FILEID="ALTO0003" BEGIN="P3_TB00008"/>
											</fptr>
										</div>
									</div>
								</div>
							</div>
							<div ID="DIVL46" TYPE="ARTICLE" ORDER="1" DMDID="MODSMD_ARTICLE4" LABEL="THE ATTRACTIONS OF OXFORD.">
								<div ID="DIVL47" TYPE="HEADING">
									<div ID="DIVL48" TYPE="TITLE">
										<fptr>
											<area BETYPE="IDREF" FILEID="ALTO0003" BEGIN="P3_TB00009"/>
										</fptr>
									</div>
								</div>
								<div ID="DIVL49" TYPE="BODY">
									<div ID="DIVL50" TYPE="BODY_CONTENT">
										<div ID="DIVL51" TYPE="PARAGRAPH" ORDER="1">
											<div ID="DIVL52" TYPE="TEXT">
												<fptr>
													<area BETYPE="IDREF" FILEID="ALTO0003" BEGIN="P3_TB00010"/>
												</fptr>
											</div>
										</div>
										<div ID="DIVL53" TYPE="PARAGRAPH" ORDER="2">
											<div ID="DIVL54" TYPE="TEXT">
												<fptr>
													<area BETYPE="IDREF" FILEID="ALTO0003" BEGIN="P3_TB00011"/>
												</fptr>
											</div>
										</div>
									</div>
								</div>
							</div>
							<div ID="DIVL55" TYPE="ARTICLE" ORDER="2" DMDID="MODSMD_ARTICLE5" LABEL="SALVATION ARMY.">
								<div ID="DIVL56" TYPE="HEADING">
									<div ID="DIVL57" TYPE="TITLE">
										<fptr>
											<area BETYPE="IDREF" FILEID="ALTO0003" BEGIN="P3_TB00012"/>
										</fptr>
									</div>
								</div>
								<div ID="DIVL58" TYPE="BODY">
									<div ID="DIVL59" TYPE="BODY_CONTENT">
										<div ID="DIVL60" TYPE="PARAGRAPH" ORDER="1">
											<div ID="DIVL61" TYPE="TEXT">
												<fptr>
													<seq>
														<area BETYPE="IDREF" FILEID="ALTO0003" BEGIN="P3_TB00013"/>
														<area BETYPE="IDREF" FILEID="ALTO0003" BEGIN="P3_TB00014"/>
													</seq>
												</fptr>
											</div>
										</div>
										<div ID="DIVL62" TYPE="PARAGRAPH" ORDER="2">
											<div ID="DIVL63" TYPE="TEXT">
												<fptr>
													<area BETYPE="IDREF" FILEID="ALTO0003" BEGIN="P3_TB00015"/>
												</fptr>
											</div>
										</div>
									</div>
								</div>
							</div>
						</div>
						<div ID="DIVL64" TYPE="ARTICLE" DMDID="MODSMD_ARTICLE6" LABEL='"WHY DO THE BEST MEN LEAVE THE CHURCH"?'>
							<div ID="DIVL65" TYPE="HEADING">
								<div ID="DIVL66" TYPE="TITLE">
									<fptr>
										<area BETYPE="IDREF" FILEID="ALTO0003" BEGIN="P3_TB00016"/>
									</fptr>
								</div>
							</div>
							<div ID="DIVL67" TYPE="BODY">
								<div ID="DIVL68" TYPE="BODY_CONTENT">
									<div ID="DIVL69" TYPE="PARAGRAPH" ORDER="1">
										<div ID="DIVL70" TYPE="TEXT">
											<fptr>
												<area BETYPE="IDREF" FILEID="ALTO0003" BEGIN="P3_TB00017"/>
											</fptr>
										</div>
									</div>
									<div ID="DIVL71" TYPE="PARAGRAPH" ORDER="2">
										<div ID="DIVL72" TYPE="TEXT">
											<fptr>
												<area BETYPE="IDREF" FILEID="ALTO0003" BEGIN="P3_TB00018"/>
											</fptr>
										</div>
									</div>
									<div ID="DIVL73" TYPE="PARAGRAPH" ORDER="3">
										<div ID="DIVL74" TYPE="TEXT">
											<fptr>
												<area BETYPE="IDREF" FILEID="ALTO0003" BEGIN="P3_TB00019"/>
											</fptr>
										</div>
									</div>
									<div ID="DIVL75" TYPE="PARAGRAPH" ORDER="4">
										<div ID="DIVL76" TYPE="TEXT">
											<fptr>
												<area BETYPE="IDREF" FILEID="ALTO0003" BEGIN="P3_TB00020"/>
											</fptr>
										</div>
									</div>
									<div ID="DIVL77" TYPE="PARAGRAPH" ORDER="5">
										<div ID="DIVL78" TYPE="TEXT">
											<fptr>
												<seq>
													<area BETYPE="IDREF" FILEID="ALTO0003" BEGIN="P3_TB00021"/>
													<area BETYPE="IDREF" FILEID="ALTO0003" BEGIN="P3_TB00022"/>
												</seq>
											</fptr>
										</div>
									</div>
									<div ID="DIVL79" TYPE="PARAGRAPH" ORDER="6">
										<div ID="DIVL80" TYPE="TEXT">
											<fptr>
												<area BETYPE="IDREF" FILEID="ALTO0003" BEGIN="P3_TB00023"/>
											</fptr>
										</div>
									</div>
								</div>
							</div>
						</div>
						<div ID="DIVL81" TYPE="ARTICLE" DMDID="MODSMD_ARTICLE7" LABEL="A STRANGE PHENOMENA.">
							<div ID="DIVL82" TYPE="HEADING">
								<div ID="DIVL83" TYPE="TITLE">
									<fptr>
										<area BETYPE="IDREF" FILEID="ALTO0003" BEGIN="P3_TB00024"/>
									</fptr>
								</div>
							</div>
							<div ID="DIVL84" TYPE="BODY">
								<div ID="DIVL85" TYPE="BODY_CONTENT">
									<div ID="DIVL86" TYPE="PARAGRAPH" ORDER="1">
										<div ID="DIVL87" TYPE="TEXT">
											<fptr>
												<area BETYPE="IDREF" FILEID="ALTO0003" BEGIN="P3_TB00025"/>
											</fptr>
										</div>
									</div>
									<div ID="DIVL88" TYPE="PARAGRAPH" ORDER="2">
										<div ID="DIVL89" TYPE="TEXT">
											<fptr>
												<area BETYPE="IDREF" FILEID="ALTO0003" BEGIN="P3_TB00026"/>
											</fptr>
										</div>
									</div>
								</div>
							</div>
						</div>
						<div ID="DIVL90" TYPE="ARTICLE" DMDID="MODSMD_ARTICLE8" LABEL="ACCIDENTS.">
							<div ID="DIVL91" TYPE="HEADING">
								<div ID="DIVL92" TYPE="TITLE">
									<fptr>
										<area BETYPE="IDREF" FILEID="ALTO0003" BEGIN="P3_TB00027"/>
									</fptr>
								</div>
							</div>
							<div ID="DIVL93" TYPE="BODY">
								<div ID="DIVL94" TYPE="BODY_CONTENT">
									<div ID="DIVL95" TYPE="PARAGRAPH" ORDER="1">
										<div ID="DIVL96" TYPE="TEXT">
											<fptr>
												<area BETYPE="IDREF" FILEID="ALTO0003" BEGIN="P3_TB00028"/>
											</fptr>
										</div>
									</div>
									<div ID="DIVL97" TYPE="PARAGRAPH" ORDER="2">
										<div ID="DIVL98" TYPE="TEXT">
											<fptr>
												<area BETYPE="IDREF" FILEID="ALTO0003" BEGIN="P3_TB00029"/>
											</fptr>
										</div>
									</div>
									<div ID="DIVL99" TYPE="PARAGRAPH" ORDER="3">
										<div ID="DIVL100" TYPE="TEXT">
											<fptr>
												<area BETYPE="IDREF" FILEID="ALTO0003" BEGIN="P3_TB00030"/>
											</fptr>
										</div>
									</div>
								</div>
							</div>
						</div>
						<div ID="DIVL101" TYPE="ARTICLE" DMDID="MODSMD_ARTICLE9" LABEL="NOTES AND NOTIONS.">
							<div ID="DIVL102" TYPE="HEADING">
								<div ID="DIVL103" TYPE="TITLE">
									<fptr>
										<area BETYPE="IDREF" FILEID="ALTO0003" BEGIN="P3_TB00031"/>
									</fptr>
								</div>
							</div>
							<div ID="DIVL104" TYPE="BODY">
								<div ID="DIVL105" TYPE="BODY_CONTENT">
									<div ID="DIVL106" TYPE="PARAGRAPH" ORDER="1">
										<div ID="DIVL107" TYPE="TEXT">
											<fptr>
												<area BETYPE="IDREF" FILEID="ALTO0003" BEGIN="P3_TB00032"/>
											</fptr>
										</div>
									</div>
								</div>
							</div>
						</div>
						<div ID="DIVL108" TYPE="ARTICLE" DMDID="MODSMD_ARTICLE10" LABEL="A SUPERIOR KIND OF COW.">
							<div ID="DIVL109" TYPE="HEADING">
								<div ID="DIVL110" TYPE="TITLE">
									<fptr>
										<area BETYPE="IDREF" FILEID="ALTO0003" BEGIN="P3_TB00033"/>
									</fptr>
								</div>
							</div>
							<div ID="DIVL111" TYPE="BODY">
								<div ID="DIVL112" TYPE="BODY_CONTENT">
									<div ID="DIVL113" TYPE="PARAGRAPH" ORDER="1">
										<div ID="DIVL114" TYPE="TEXT">
											<fptr>
												<seq>
													<area BETYPE="IDREF" FILEID="ALTO0003" BEGIN="P3_TB00034"/>
													<area BETYPE="IDREF" FILEID="ALTO0003" BEGIN="P3_TB00035"/>
												</seq>
											</fptr>
										</div>
									</div>
								</div>
							</div>
						</div>
						<div ID="DIVL115" TYPE="ARTICLE" DMDID="MODSMD_ARTICLE11" LABEL="COOLGARDIE.">
							<div ID="DIVL116" TYPE="HEADING">
								<div ID="DIVL117" TYPE="TITLE">
									<fptr>
										<area BETYPE="IDREF" FILEID="ALTO0003" BEGIN="P3_TB00036"/>
									</fptr>
								</div>
							</div>
							<div ID="DIVL118" TYPE="BODY">
								<div ID="DIVL119" TYPE="BODY_CONTENT">
									<div ID="DIVL120" TYPE="PARAGRAPH" ORDER="1">
										<div ID="DIVL121" TYPE="TEXT">
											<fptr>
												<area BETYPE="IDREF" FILEID="ALTO0003" BEGIN="P3_TB00037"/>
											</fptr>
										</div>
									</div>
									<div ID="DIVL122" TYPE="PARAGRAPH" ORDER="2">
										<div ID="DIVL123" TYPE="TEXT">
											<fptr>
												<area BETYPE="IDREF" FILEID="ALTO0003" BEGIN="P3_TB00038"/>
											</fptr>
										</div>
									</div>
									<div ID="DIVL124" TYPE="PARAGRAPH" ORDER="3">
										<div ID="DIVL125" TYPE="TEXT">
											<fptr>
												<seq>
													<area BETYPE="IDREF" FILEID="ALTO0003" BEGIN="P3_TB00039"/>
													<area BETYPE="IDREF" FILEID="ALTO0003" BEGIN="P3_TB00040"/>
												</seq>
											</fptr>
										</div>
									</div>
								</div>
							</div>
						</div>
						<div ID="DIVL126" TYPE="ARTICLE" DMDID="MODSMD_ARTICLE12" LABEL="LOCAL AND GENERAL">
							<div ID="DIVL127" TYPE="HEADING">
								<div ID="DIVL128" TYPE="TITLE">
									<fptr>
										<area BETYPE="IDREF" FILEID="ALTO0003" BEGIN="P3_TB00041"/>
									</fptr>
								</div>
							</div>
							<div ID="DIVL129" TYPE="BODY">
								<div ID="DIVL130" TYPE="BODY_CONTENT">
									<div ID="DIVL131" TYPE="PARAGRAPH" ORDER="1">
										<div ID="DIVL132" TYPE="TEXT">
											<fptr>
												<area BETYPE="IDREF" FILEID="ALTO0003" BEGIN="P3_TB00042"/>
											</fptr>
										</div>
									</div>
									<div ID="DIVL133" TYPE="PARAGRAPH" ORDER="2">
										<div ID="DIVL134" TYPE="TEXT">
											<fptr>
												<area BETYPE="IDREF" FILEID="ALTO0003" BEGIN="P3_TB00043"/>
											</fptr>
										</div>
									</div>
								</div>
							</div>
						</div>
						<div ID="DIVL135" TYPE="ARTICLE" DMDID="MODSMD_ARTICLE13" LABEL="PHOTOGRAPHY OF STARS.">
							<div ID="DIVL136" TYPE="HEADING">
								<div ID="DIVL137" TYPE="TITLE">
									<fptr>
										<area BETYPE="IDREF" FILEID="ALTO0003" BEGIN="P3_TB00044"/>
									</fptr>
								</div>
							</div>
							<div ID="DIVL138" TYPE="BODY">
								<div ID="DIVL139" TYPE="BODY_CONTENT">
									<div ID="DIVL140" TYPE="PARAGRAPH" ORDER="1">
										<div ID="DIVL141" TYPE="TEXT">
											<fptr>
												<area BETYPE="IDREF" FILEID="ALTO0003" BEGIN="P3_TB00045"/>
											</fptr>
										</div>
									</div>
								</div>
							</div>
						</div>
						<div ID="DIVL142" TYPE="ARTICLE" DMDID="MODSMD_ARTICLE14" LABEL="OXFORD LIBRARY AND READING ROOM.">
							<div ID="DIVL143" TYPE="HEADING">
								<div ID="DIVL144" TYPE="TITLE">
									<fptr>
										<area BETYPE="IDREF" FILEID="ALTO0004" BEGIN="P4_TB00001"/>
									</fptr>
								</div>
							</div>
							<div ID="DIVL145" TYPE="BODY">
								<div ID="DIVL146" TYPE="BODY_CONTENT">
									<div ID="DIVL147" TYPE="PARAGRAPH" ORDER="1">
										<div ID="DIVL148" TYPE="TEXT">
											<fptr>
												<area BETYPE="IDREF" FILEID="ALTO0004" BEGIN="P4_TB00002"/>
											</fptr>
										</div>
									</div>
								</div>
							</div>
						</div>
						<div ID="DIVL149" TYPE="ARTICLE" DMDID="MODSMD_ARTICLE15" LABEL="THE CHEAP MONEY SCHEME.">
							<div ID="DIVL150" TYPE="HEADING">
								<div ID="DIVL151" TYPE="TITLE">
									<fptr>
										<area BETYPE="IDREF" FILEID="ALTO0004" BEGIN="P4_TB00003"/>
									</fptr>
								</div>
							</div>
							<div ID="DIVL152" TYPE="BODY">
								<div ID="DIVL153" TYPE="BODY_CONTENT">
									<div ID="DIVL154" TYPE="PARAGRAPH" ORDER="1">
										<div ID="DIVL155" TYPE="TEXT">
											<fptr>
												<area BETYPE="IDREF" FILEID="ALTO0004" BEGIN="P4_TB00004"/>
											</fptr>
										</div>
									</div>
								</div>
							</div>
						</div>
						<div ID="DIVL156" TYPE="SECTION" DMDID="MODSMD_SECTION2">
							<div ID="DIVL157" TYPE="BODY">
								<div ID="DIVL158" TYPE="BODY_CONTENT">
									<div ID="DIVL159" TYPE="ADVERTISEMENT" ORDER="1" LABEL="Adv. 1 Page 4">
										<fptr>
											<area BETYPE="IDREF" FILEID="ALTO0004" BEGIN="P4_CB00001"/>
										</fptr>
									</div>
									<div ID="DIVL160" TYPE="ADVERTISEMENT" ORDER="2" LABEL="Adv. 2 Page 4">
										<fptr>
											<area BETYPE="IDREF" FILEID="ALTO0004" BEGIN="P4_CB00002"/>
										</fptr>
									</div>
									<div ID="DIVL161" TYPE="ADVERTISEMENT" ORDER="3" LABEL="Adv. 3 Page 4">
										<fptr>
											<area BETYPE="IDREF" FILEID="ALTO0004" BEGIN="P4_CB00003"/>
										</fptr>
									</div>
									<div ID="DIVL162" TYPE="ADVERTISEMENT" ORDER="4" LABEL="Adv. 4 Page 4">
										<fptr>
											<area BETYPE="IDREF" FILEID="ALTO0004" BEGIN="P4_CB00004"/>
										</fptr>
									</div>
									<div ID="DIVL163" TYPE="ADVERTISEMENT" ORDER="5" LABEL="Adv. 5 Page 4">
										<fptr>
											<area BETYPE="IDREF" FILEID="ALTO0004" BEGIN="P4_CB00005"/>
										</fptr>
									</div>
									<div ID="DIVL164" TYPE="ADVERTISEMENT" ORDER="6" LABEL="Adv. 6 Page 2">
										<fptr>
											<area BETYPE="IDREF" FILEID="ALTO0002" BEGIN="P2_CB00001"/>
										</fptr>
									</div>
									<div ID="DIVL165" TYPE="ADVERTISEMENT" ORDER="7" LABEL="Adv. 7 Page 2">
										<fptr>
											<area BETYPE="IDREF" FILEID="ALTO0002" BEGIN="P2_CB00002"/>
										</fptr>
									</div>
									<div ID="DIVL166" TYPE="ADVERTISEMENT" ORDER="8" LABEL="Adv. 8 Page 2">
										<fptr>
											<area BETYPE="IDREF" FILEID="ALTO0002" BEGIN="P2_CB00003"/>
										</fptr>
									</div>
									<div ID="DIVL167" TYPE="ADVERTISEMENT" ORDER="9" LABEL="Adv. 9 Page 2">
										<fptr>
											<area BETYPE="IDREF" FILEID="ALTO0002" BEGIN="P2_CB00004"/>
										</fptr>
									</div>
									<div ID="DIVL168" TYPE="ADVERTISEMENT" ORDER="10" LABEL="Adv. 10 Page 2">
										<fptr>
											<area BETYPE="IDREF" FILEID="ALTO0002" BEGIN="P2_CB00005"/>
										</fptr>
									</div>
									<div ID="DIVL169" TYPE="ADVERTISEMENT" ORDER="11" LABEL="Adv. 11 Page 1">
										<fptr>
											<area BETYPE="IDREF" FILEID="ALTO0001" BEGIN="P1_CB00001"/>
										</fptr>
									</div>
									<div ID="DIVL170" TYPE="ADVERTISEMENT" ORDER="12" LABEL="Adv. 12 Page 1">
										<fptr>
											<area BETYPE="IDREF" FILEID="ALTO0001" BEGIN="P1_CB00002"/>
										</fptr>
									</div>
									<div ID="DIVL171" TYPE="ADVERTISEMENT" ORDER="13" LABEL="Adv. 13 Page 1">
										<fptr>
											<area BETYPE="IDREF" FILEID="ALTO0001" BEGIN="P1_CB00003"/>
										</fptr>
									</div>
									<div ID="DIVL172" TYPE="ADVERTISEMENT" ORDER="14" LABEL="Adv. 14 Page 1">
										<fptr>
											<area BETYPE="IDREF" FILEID="ALTO0001" BEGIN="P1_CB00004"/>
										</fptr>
									</div>
									<div ID="DIVL173" TYPE="ADVERTISEMENT" ORDER="15" LABEL="Adv. 15 Page 1">
										<fptr>
											<area BETYPE="IDREF" FILEID="ALTO0001" BEGIN="P1_CB00005"/>
										</fptr>
									</div>
									<div ID="DIVL174" TYPE="ADVERTISEMENT" ORDER="16" LABEL="Adv. 16 Page 1">
										<fptr>
											<area BETYPE="IDREF" FILEID="ALTO0001" BEGIN="P1_CB00006"/>
										</fptr>
									</div>
									<div ID="DIVL175" TYPE="ADVERTISEMENT" ORDER="17" LABEL="Adv. 17 Page 1">
										<fptr>
											<area BETYPE="IDREF" FILEID="ALTO0001" BEGIN="P1_CB00007"/>
										</fptr>
									</div>
								</div>
							</div>
						</div>
					</div>
				</div>
			</div>
		</div>
	</structMap>
</mets>
