<?xml version="1.0" encoding="UTF-8"?>
<mets xmlns:xsi="http://www.w3.org/2001/XMLSchema-instance" xmlns="http://www.loc.gov/METS/" xsi:schemaLocation="http://www.loc.gov/METS/ //docstorage/impdata$/docWORKS/schema/mets-metae.xsd" xmlns:MODS="http://www.loc.gov/mods/v3" xmlns:mix="http://www.loc.gov/mix/" xmlns:xlink="http://www.w3.org/TR/xlink" TYPE="Newspaper" LABEL="New Zealand Gazette and Wellington Spectator no. 177 1842-09-17">
	<metsHdr CREATEDATE="2007-07-16T21:58:38" LASTMODDATE="2007-07-16T21:58:38">
		<agent ROLE="CREATOR" TYPE="OTHER" OTHERTYPE="SOFTWARE">
			<name>CCS docWORKS/METAe Version 6.0-8</name>
		</agent>
	</metsHdr>
	<dmdSec ID="MODSMD_PRINT">
		<mdWrap MIMETYPE="text/xml" MDTYPE="MODS" LABEL="Bibliographic meta-data of the printed version">
			<xmlData>
				<MODS:mods>
					<MODS:titleInfo ID="MODSMD_PRINT_TI1" xml:lang="en">
						<MODS:title>New Zealand Gazette and Wellington Spectator</MODS:title>
						<MODS:partNumber>III</MODS:partNumber>
					</MODS:titleInfo>
					<MODS:language>
						<MODS:languageTerm type="code" authority="rfc3066">en</MODS:languageTerm>
					</MODS:language>
					<MODS:originInfo>
						<MODS:dateIssued encoding="w3cdtf" point="start" keyDate="yes" qualifier="approximate">1842-09-17</MODS:dateIssued>
					</MODS:originInfo>
					<MODS:identifier type="local">NZGWS_18420917</MODS:identifier>
					<MODS:titleInfo ID="MODSMD_PRINT_TI2" type="alternative">
						<MODS:title>New Zealand Gazette;New Zealand Gazette and Britannia Spectator;Wellington Spectator;Britannia Spectator</MODS:title>
					</MODS:titleInfo>
				</MODS:mods>
			</xmlData>
		</mdWrap>
	</dmdSec>
	<dmdSec ID="MODSMD_ELEC">
		<mdWrap MIMETYPE="text/xml" MDTYPE="MODS" LABEL="Bibliographic meta-data of the electronic version">
			<xmlData>
				<MODS:mods>
					<MODS:originInfo>
						<MODS:dateCreated point="start" keyDate="yes" qualifier="approximate">2007-07-16</MODS:dateCreated>
						<MODS:publisher>CCS Content Conversion Specialists GmbH</MODS:publisher>
					</MODS:originInfo>
					<MODS:titleInfo ID="MODSMD_ELEC_TI1" xml:lang="en">
						<MODS:title>New Zealand Gazette and Wellington Spectator</MODS:title>
						<MODS:partNumber>III</MODS:partNumber>
					</MODS:titleInfo>
					<MODS:language>
						<MODS:languageTerm type="code" authority="rfc3066">en</MODS:languageTerm>
					</MODS:language>
					<MODS:identifier type="local">NZGWS_18420917</MODS:identifier>
					<MODS:titleInfo ID="MODSMD_ELEC_TI2" type="alternative">
						<MODS:title>New Zealand Gazette;New Zealand Gazette and Britannia Spectator;Wellington Spectator;Britannia Spectator</MODS:title>
					</MODS:titleInfo>
				</MODS:mods>
			</xmlData>
		</mdWrap>
	</dmdSec>
	<dmdSec ID="MODSMD_ISSUE1">
		<mdWrap MIMETYPE="text/xml" MDTYPE="MODS" LABEL="Bibliographic meta-data of Issue">
			<xmlData>
				<MODS:mods>
					<MODS:titleInfo ID="MODSMD_ISSUE1_TI1" xml:lang="en">
						<MODS:title>New Zealand Gazette and Wellington Spectator</MODS:title>
						<MODS:partNumber>177</MODS:partNumber>
					</MODS:titleInfo>
					<MODS:language>
						<MODS:languageTerm type="code" authority="rfc3066">en</MODS:languageTerm>
					</MODS:language>
					<MODS:originInfo>
						<MODS:dateIssued encoding="w3cdtf" point="start" keyDate="yes" qualifier="approximate">1842-09-17</MODS:dateIssued>
					</MODS:originInfo>
					<MODS:identifier type="local">NZGWS_18420917</MODS:identifier>
					<MODS:relatedItem ID="MODSMD_ISSUE1_RI1" type="host">
						<MODS:identifier type="local">III</MODS:identifier>
					</MODS:relatedItem>
					<MODS:titleInfo ID="MODSMD_ISSUE1_TI2" type="alternative">
						<MODS:title>New Zealand Gazette;New Zealand Gazette and Britannia Spectator;Wellington Spectator;Britannia Spectator</MODS:title>
					</MODS:titleInfo>
				</MODS:mods>
			</xmlData>
		</mdWrap>
	</dmdSec>
	<dmdSec ID="MODSMD_ARTICLE1">
		<mdWrap MIMETYPE="text/xml" MDTYPE="MODS" LABEL="Bibliographic meta-data of article">
			<xmlData>
				<MODS:mods>
					<MODS:titleInfo ID="MODSMD_ARTICLE1_TI1" xml:lang="en">
						<MODS:title>THE NEW ZEALAND GAZETTE AND</MODS:title>
					</MODS:titleInfo>
					<MODS:language>
						<MODS:languageTerm type="code" authority="rfc3066">en</MODS:languageTerm>
					</MODS:language>
				</MODS:mods>
			</xmlData>
		</mdWrap>
	</dmdSec>
	<dmdSec ID="MODSMD_ARTICLE2">
		<mdWrap MIMETYPE="text/xml" MDTYPE="MODS" LABEL="Bibliographic meta-data of article">
			<xmlData>
				<MODS:mods>
					<MODS:titleInfo ID="MODSMD_ARTICLE2_TI2" xml:lang="en">
						<MODS:title>SHIPPING INTELLIGENCE.</MODS:title>
					</MODS:titleInfo>
					<MODS:language>
						<MODS:languageTerm type="code" authority="rfc3066">en</MODS:languageTerm>
					</MODS:language>
				</MODS:mods>
			</xmlData>
		</mdWrap>
	</dmdSec>
	<dmdSec ID="MODSMD_ARTICLE3">
		<mdWrap MIMETYPE="text/xml" MDTYPE="MODS" LABEL="Bibliographic meta-data of article">
			<xmlData>
				<MODS:mods>
					<MODS:titleInfo ID="MODSMD_ARTICLE3_TI3" xml:lang="en">
						<MODS:title>IN PORT.</MODS:title>
					</MODS:titleInfo>
					<MODS:language>
						<MODS:languageTerm type="code" authority="rfc3066">en</MODS:languageTerm>
					</MODS:language>
				</MODS:mods>
			</xmlData>
		</mdWrap>
	</dmdSec>
	<dmdSec ID="MODSMD_ARTICLE4">
		<mdWrap MIMETYPE="text/xml" MDTYPE="MODS" LABEL="Bibliographic meta-data of article">
			<xmlData>
				<MODS:mods>
					<MODS:titleInfo ID="MODSMD_ARTICLE4_TI4" xml:lang="en">
						<MODS:title>CUSTOM HOUSE.</MODS:title>
					</MODS:titleInfo>
					<MODS:language>
						<MODS:languageTerm type="code" authority="rfc3066">en</MODS:languageTerm>
					</MODS:language>
				</MODS:mods>
			</xmlData>
		</mdWrap>
	</dmdSec>
	<dmdSec ID="MODSMD_ARTICLE5">
		<mdWrap MIMETYPE="text/xml" MDTYPE="MODS" LABEL="Bibliographic meta-data of article">
			<xmlData>
				<MODS:mods>
					<MODS:titleInfo ID="MODSMD_ARTICLE5_TI5" xml:lang="en">
						<MODS:title>METEOROLOGICAL TABLE.</MODS:title>
					</MODS:titleInfo>
					<MODS:language>
						<MODS:languageTerm type="code" authority="rfc3066">en</MODS:languageTerm>
					</MODS:language>
				</MODS:mods>
			</xmlData>
		</mdWrap>
	</dmdSec>
	<dmdSec ID="MODSMD_PICT1">
		<mdWrap MIMETYPE="text/xml" MDTYPE="MODS" LABEL="Bibliographic meta-data of table">
			<xmlData>
				<MODS:mods>
					<MODS:titleInfo ID="MODSMD_PICT1_TI1" xml:lang="en">
						<MODS:title>Untitled</MODS:title>
					</MODS:titleInfo>
				</MODS:mods>
			</xmlData>
		</mdWrap>
	</dmdSec>
	<dmdSec ID="MODSMD_ARTICLE6">
		<mdWrap MIMETYPE="text/xml" MDTYPE="MODS" LABEL="Bibliographic meta-data of article">
			<xmlData>
				<MODS:mods>
					<MODS:titleInfo ID="MODSMD_ARTICLE6_TI6" xml:lang="en">
						<MODS:title>New Zealand Gazette</MODS:title>
					</MODS:titleInfo>
					<MODS:language>
						<MODS:languageTerm type="code" authority="rfc3066">en</MODS:languageTerm>
					</MODS:language>
				</MODS:mods>
			</xmlData>
		</mdWrap>
	</dmdSec>
	<dmdSec ID="MODSMD_ARTICLE7">
		<mdWrap MIMETYPE="text/xml" MDTYPE="MODS" LABEL="Bibliographic meta-data of article">
			<xmlData>
				<MODS:mods>
					<MODS:titleInfo ID="MODSMD_ARTICLE7_TI7" xml:lang="en">
						<MODS:title>PUBLIC MEETING.</MODS:title>
					</MODS:titleInfo>
					<MODS:language>
						<MODS:languageTerm type="code" authority="rfc3066">en</MODS:languageTerm>
					</MODS:language>
				</MODS:mods>
			</xmlData>
		</mdWrap>
	</dmdSec>
	<dmdSec ID="MODSMD_ARTICLE8">
		<mdWrap MIMETYPE="text/xml" MDTYPE="MODS" LABEL="Bibliographic meta-data of article">
			<xmlData>
				<MODS:mods>
					<MODS:titleInfo ID="MODSMD_ARTICLE8_TI8" xml:lang="en">
						<MODS:title>EXTRACTS.</MODS:title>
					</MODS:titleInfo>
					<MODS:language>
						<MODS:languageTerm type="code" authority="rfc3066">en</MODS:languageTerm>
					</MODS:language>
				</MODS:mods>
			</xmlData>
		</mdWrap>
	</dmdSec>
	<dmdSec ID="MODSMD_SECTION1">
		<mdWrap MIMETYPE="text/xml" MDTYPE="MODS" LABEL="Bibliographic meta-data of section">
			<xmlData>
				<MODS:mods>
					<MODS:language>
						<MODS:languageTerm type="code" authority="rfc3066">en</MODS:languageTerm>
					</MODS:language>
				</MODS:mods>
			</xmlData>
		</mdWrap>
	</dmdSec>
	<amdSec ID="IMGPARAM00001">
		<techMD ID="IMGPARAM00001TECHMD">
			<mdWrap MDTYPE="NISOIMG">
				<xmlData>
					<mix:mix>
						<mix:BasicImageParameters>
							<mix:Format>
								<mix:MIMEType>image/tiff</mix:MIMEType>
								<mix:ByteOrder>little-endian</mix:ByteOrder>
								<mix:Compression>
									<mix:CompressionScheme>4</mix:CompressionScheme>
								</mix:Compression>
								<mix:PhotometricInterpretation>
									<mix:ColorSpace>1</mix:ColorSpace>
								</mix:PhotometricInterpretation>
							</mix:Format>
							<mix:File>
								<mix:ImageIdentifier imageIdentifierLocation="//docstorage/impdata$/OUT/NZ/NZGWS/NZGWS_18420917/MM_01">0001.tif</mix:ImageIdentifier>
								<mix:FileSize>405031</mix:FileSize>
								<mix:Orientation>1</mix:Orientation>
								<mix:DisplayOrientation>1</mix:DisplayOrientation>
							</mix:File>
						</mix:BasicImageParameters>
						<mix:ImageCreation>
							<mix:SourceType>Newspaper</mix:SourceType>
							<mix:SourceID/>
							<mix:ImageProducer/>
							<mix:Host>
								<mix:HostComputer>BLADESERVER-18</mix:HostComputer>
								<mix:OperatingSystem>windows</mix:OperatingSystem>
								<mix:OSVersion>5.2 Service Pack 2</mix:OSVersion>
							</mix:Host>
							<mix:DeviceSource/>
							<mix:ScanningSystemCapture>
								<mix:ScanningSystemHardware>
									<mix:ScannerManufacturer/>
									<mix:ScannerModel>
										<mix:ScannerModelName/>
										<mix:ScannerModelNumber/>
										<mix:ScannerModelSerialNo/>
									</mix:ScannerModel>
								</mix:ScanningSystemHardware>
								<mix:ScanningSystemSoftware>
									<mix:ScanningSoftware>CCS docWORKS</mix:ScanningSoftware>
									<mix:ScanningSoftwareVersionNo/>
								</mix:ScanningSystemSoftware>
								<mix:ScannerCaptureSettings>
									<mix:PixelSize>0.0635000</mix:PixelSize>
									<mix:PhysScanResolution>
										<mix:XphysScanResolution>400</mix:XphysScanResolution>
										<mix:YphysScanResolution>400</mix:YphysScanResolution>
									</mix:PhysScanResolution>
								</mix:ScannerCaptureSettings>
							</mix:ScanningSystemCapture>
						</mix:ImageCreation>
						<mix:ImagingPerformanceAssessment>
							<mix:SpatialMetrics>
								<mix:ImageWidth>4031</mix:ImageWidth>
								<mix:ImageLength>6362</mix:ImageLength>
							</mix:SpatialMetrics>
							<mix:Energetics>
								<mix:BitsPerSample>1</mix:BitsPerSample>
								<mix:SamplesPerPixel>1</mix:SamplesPerPixel>
							</mix:Energetics>
						</mix:ImagingPerformanceAssessment>
						<mix:ChangeHistory>
							<mix:ImageProcessing>
								<mix:SourceData>./NZ_2/5th HDD/PP 20007-03/NZGWS/1842/09/17/00100.TIF</mix:SourceData>
							</mix:ImageProcessing>
						</mix:ChangeHistory>
					</mix:mix>
				</xmlData>
			</mdWrap>
		</techMD>
	</amdSec>
	<amdSec ID="IMGPARAM00002">
		<techMD ID="IMGPARAM00002TECHMD">
			<mdWrap MDTYPE="NISOIMG">
				<xmlData>
					<mix:mix>
						<mix:BasicImageParameters>
							<mix:Format>
								<mix:MIMEType>image/tiff</mix:MIMEType>
								<mix:ByteOrder>little-endian</mix:ByteOrder>
								<mix:Compression>
									<mix:CompressionScheme>4</mix:CompressionScheme>
								</mix:Compression>
								<mix:PhotometricInterpretation>
									<mix:ColorSpace>1</mix:ColorSpace>
								</mix:PhotometricInterpretation>
							</mix:Format>
							<mix:File>
								<mix:ImageIdentifier imageIdentifierLocation="//docstorage/impdata$/OUT/NZ/NZGWS/NZGWS_18420917/MM_01">0002.tif</mix:ImageIdentifier>
								<mix:FileSize>478022</mix:FileSize>
								<mix:Orientation>1</mix:Orientation>
								<mix:DisplayOrientation>1</mix:DisplayOrientation>
							</mix:File>
						</mix:BasicImageParameters>
						<mix:ImageCreation>
							<mix:SourceType>Newspaper</mix:SourceType>
							<mix:SourceID/>
							<mix:ImageProducer/>
							<mix:Host>
								<mix:HostComputer>BLADESERVER-18</mix:HostComputer>
								<mix:OperatingSystem>windows</mix:OperatingSystem>
								<mix:OSVersion>5.2 Service Pack 2</mix:OSVersion>
							</mix:Host>
							<mix:DeviceSource/>
							<mix:ScanningSystemCapture>
								<mix:ScanningSystemHardware>
									<mix:ScannerManufacturer/>
									<mix:ScannerModel>
										<mix:ScannerModelName/>
										<mix:ScannerModelNumber/>
										<mix:ScannerModelSerialNo/>
									</mix:ScannerModel>
								</mix:ScanningSystemHardware>
								<mix:ScanningSystemSoftware>
									<mix:ScanningSoftware>CCS docWORKS</mix:ScanningSoftware>
									<mix:ScanningSoftwareVersionNo/>
								</mix:ScanningSystemSoftware>
								<mix:ScannerCaptureSettings>
									<mix:PixelSize>0.0635000</mix:PixelSize>
									<mix:PhysScanResolution>
										<mix:XphysScanResolution>400</mix:XphysScanResolution>
										<mix:YphysScanResolution>400</mix:YphysScanResolution>
									</mix:PhysScanResolution>
								</mix:ScannerCaptureSettings>
							</mix:ScanningSystemCapture>
						</mix:ImageCreation>
						<mix:ImagingPerformanceAssessment>
							<mix:SpatialMetrics>
								<mix:ImageWidth>4031</mix:ImageWidth>
								<mix:ImageLength>6362</mix:ImageLength>
							</mix:SpatialMetrics>
							<mix:Energetics>
								<mix:BitsPerSample>1</mix:BitsPerSample>
								<mix:SamplesPerPixel>1</mix:SamplesPerPixel>
							</mix:Energetics>
						</mix:ImagingPerformanceAssessment>
						<mix:ChangeHistory>
							<mix:ImageProcessing>
								<mix:SourceData>./NZ_2/5th HDD/PP 20007-03/NZGWS/1842/09/17/00200.TIF</mix:SourceData>
							</mix:ImageProcessing>
						</mix:ChangeHistory>
					</mix:mix>
				</xmlData>
			</mdWrap>
		</techMD>
	</amdSec>
	<amdSec ID="IMGPARAM00003">
		<techMD ID="IMGPARAM00003TECHMD">
			<mdWrap MDTYPE="NISOIMG">
				<xmlData>
					<mix:mix>
						<mix:BasicImageParameters>
							<mix:Format>
								<mix:MIMEType>image/tiff</mix:MIMEType>
								<mix:ByteOrder>little-endian</mix:ByteOrder>
								<mix:Compression>
									<mix:CompressionScheme>4</mix:CompressionScheme>
								</mix:Compression>
								<mix:PhotometricInterpretation>
									<mix:ColorSpace>1</mix:ColorSpace>
								</mix:PhotometricInterpretation>
							</mix:Format>
							<mix:File>
								<mix:ImageIdentifier imageIdentifierLocation="//docstorage/impdata$/OUT/NZ/NZGWS/NZGWS_18420917/MM_01">0003.tif</mix:ImageIdentifier>
								<mix:FileSize>510790</mix:FileSize>
								<mix:Orientation>1</mix:Orientation>
								<mix:DisplayOrientation>1</mix:DisplayOrientation>
							</mix:File>
						</mix:BasicImageParameters>
						<mix:ImageCreation>
							<mix:SourceType>Newspaper</mix:SourceType>
							<mix:SourceID/>
							<mix:ImageProducer/>
							<mix:Host>
								<mix:HostComputer>BLADESERVER-18</mix:HostComputer>
								<mix:OperatingSystem>windows</mix:OperatingSystem>
								<mix:OSVersion>5.2 Service Pack 2</mix:OSVersion>
							</mix:Host>
							<mix:DeviceSource/>
							<mix:ScanningSystemCapture>
								<mix:ScanningSystemHardware>
									<mix:ScannerManufacturer/>
									<mix:ScannerModel>
										<mix:ScannerModelName/>
										<mix:ScannerModelNumber/>
										<mix:ScannerModelSerialNo/>
									</mix:ScannerModel>
								</mix:ScanningSystemHardware>
								<mix:ScanningSystemSoftware>
									<mix:ScanningSoftware>CCS docWORKS</mix:ScanningSoftware>
									<mix:ScanningSoftwareVersionNo/>
								</mix:ScanningSystemSoftware>
								<mix:ScannerCaptureSettings>
									<mix:PixelSize>0.0635000</mix:PixelSize>
									<mix:PhysScanResolution>
										<mix:XphysScanResolution>400</mix:XphysScanResolution>
										<mix:YphysScanResolution>400</mix:YphysScanResolution>
									</mix:PhysScanResolution>
								</mix:ScannerCaptureSettings>
							</mix:ScanningSystemCapture>
						</mix:ImageCreation>
						<mix:ImagingPerformanceAssessment>
							<mix:SpatialMetrics>
								<mix:ImageWidth>4031</mix:ImageWidth>
								<mix:ImageLength>6362</mix:ImageLength>
							</mix:SpatialMetrics>
							<mix:Energetics>
								<mix:BitsPerSample>1</mix:BitsPerSample>
								<mix:SamplesPerPixel>1</mix:SamplesPerPixel>
							</mix:Energetics>
						</mix:ImagingPerformanceAssessment>
						<mix:ChangeHistory>
							<mix:ImageProcessing>
								<mix:SourceData>./NZ_2/5th HDD/PP 20007-03/NZGWS/1842/09/17/00300.TIF</mix:SourceData>
							</mix:ImageProcessing>
						</mix:ChangeHistory>
					</mix:mix>
				</xmlData>
			</mdWrap>
		</techMD>
	</amdSec>
	<amdSec ID="IMGPARAM00004">
		<techMD ID="IMGPARAM00004TECHMD">
			<mdWrap MDTYPE="NISOIMG">
				<xmlData>
					<mix:mix>
						<mix:BasicImageParameters>
							<mix:Format>
								<mix:MIMEType>image/tiff</mix:MIMEType>
								<mix:ByteOrder>little-endian</mix:ByteOrder>
								<mix:Compression>
									<mix:CompressionScheme>4</mix:CompressionScheme>
								</mix:Compression>
								<mix:PhotometricInterpretation>
									<mix:ColorSpace>1</mix:ColorSpace>
								</mix:PhotometricInterpretation>
							</mix:Format>
							<mix:File>
								<mix:ImageIdentifier imageIdentifierLocation="//docstorage/impdata$/OUT/NZ/NZGWS/NZGWS_18420917/MM_01">0004.tif</mix:ImageIdentifier>
								<mix:FileSize>429944</mix:FileSize>
								<mix:Orientation>1</mix:Orientation>
								<mix:DisplayOrientation>1</mix:DisplayOrientation>
							</mix:File>
						</mix:BasicImageParameters>
						<mix:ImageCreation>
							<mix:SourceType>Newspaper</mix:SourceType>
							<mix:SourceID/>
							<mix:ImageProducer/>
							<mix:Host>
								<mix:HostComputer>BLADESERVER-18</mix:HostComputer>
								<mix:OperatingSystem>windows</mix:OperatingSystem>
								<mix:OSVersion>5.2 Service Pack 2</mix:OSVersion>
							</mix:Host>
							<mix:DeviceSource/>
							<mix:ScanningSystemCapture>
								<mix:ScanningSystemHardware>
									<mix:ScannerManufacturer/>
									<mix:ScannerModel>
										<mix:ScannerModelName/>
										<mix:ScannerModelNumber/>
										<mix:ScannerModelSerialNo/>
									</mix:ScannerModel>
								</mix:ScanningSystemHardware>
								<mix:ScanningSystemSoftware>
									<mix:ScanningSoftware>CCS docWORKS</mix:ScanningSoftware>
									<mix:ScanningSoftwareVersionNo/>
								</mix:ScanningSystemSoftware>
								<mix:ScannerCaptureSettings>
									<mix:PixelSize>0.0635000</mix:PixelSize>
									<mix:PhysScanResolution>
										<mix:XphysScanResolution>400</mix:XphysScanResolution>
										<mix:YphysScanResolution>400</mix:YphysScanResolution>
									</mix:PhysScanResolution>
								</mix:ScannerCaptureSettings>
							</mix:ScanningSystemCapture>
						</mix:ImageCreation>
						<mix:ImagingPerformanceAssessment>
							<mix:SpatialMetrics>
								<mix:ImageWidth>4031</mix:ImageWidth>
								<mix:ImageLength>6362</mix:ImageLength>
							</mix:SpatialMetrics>
							<mix:Energetics>
								<mix:BitsPerSample>1</mix:BitsPerSample>
								<mix:SamplesPerPixel>1</mix:SamplesPerPixel>
							</mix:Energetics>
						</mix:ImagingPerformanceAssessment>
						<mix:ChangeHistory>
							<mix:ImageProcessing>
								<mix:SourceData>./NZ_2/5th HDD/PP 20007-03/NZGWS/1842/09/17/00400.TIF</mix:SourceData>
							</mix:ImageProcessing>
						</mix:ChangeHistory>
					</mix:mix>
				</xmlData>
			</mdWrap>
		</techMD>
	</amdSec>
	<fileSec>
		<fileGrp ID="IMGGRP" USE="Images">
			<file ID="IMG00001" CREATED="2007-07-16T21:58:30" ADMID="IMGPARAM00001" MIMETYPE="image/tif" SEQ="1" CHECKSUM="6b09bbbade93df6d9e4953d098b95584" CHECKSUMTYPE="MD5" SIZE="405031">
				<FLocat LOCTYPE="URL" xlink:href="file://./0001.tif"/>
			</file>
			<file ID="IMG00002" CREATED="2007-07-16T21:58:30" ADMID="IMGPARAM00002" MIMETYPE="image/tif" SEQ="2" CHECKSUM="ee36be9e4f7a565858c4855276c54db0" CHECKSUMTYPE="MD5" SIZE="478022">
				<FLocat LOCTYPE="URL" xlink:href="file://./0002.tif"/>
			</file>
			<file ID="IMG00003" CREATED="2007-07-16T21:58:30" ADMID="IMGPARAM00003" MIMETYPE="image/tif" SEQ="3" CHECKSUM="fe7b049345b4b81b4cb3a5d3acea228e" CHECKSUMTYPE="MD5" SIZE="510790">
				<FLocat LOCTYPE="URL" xlink:href="file://./0003.tif"/>
			</file>
			<file ID="IMG00004" CREATED="2007-07-16T21:58:30" ADMID="IMGPARAM00004" MIMETYPE="image/tif" SEQ="4" CHECKSUM="7d84eb1856877abfd2d6972465fe48bf" CHECKSUMTYPE="MD5" SIZE="429944">
				<FLocat LOCTYPE="URL" xlink:href="file://./0004.tif"/>
			</file>
		</fileGrp>
		<fileGrp ID="ALTOGRP" USE="Text">
			<file ID="ALTO0001" MIMETYPE="text/xml" CHECKSUM="5f4189434ab9878daeaf8b60c8a863ce" CHECKSUMTYPE="MD5" SIZE="543996">
				<FLocat LOCTYPE="URL" xlink:href="file://./0001.xml"/>
			</file>
			<file ID="ALTO0002" MIMETYPE="text/xml" CHECKSUM="0ea17d022192b76ababa0dd8af3cbb1b" CHECKSUMTYPE="MD5" SIZE="714868">
				<FLocat LOCTYPE="URL" xlink:href="file://./0002.xml"/>
			</file>
			<file ID="ALTO0003" MIMETYPE="text/xml" CHECKSUM="bec457e2f53346cc2d7337739e80093c" CHECKSUMTYPE="MD5" SIZE="762986">
				<FLocat LOCTYPE="URL" xlink:href="file://./0003.xml"/>
			</file>
			<file ID="ALTO0004" MIMETYPE="text/xml" CHECKSUM="7fce247b0231b964b7b49fed25f5c363" CHECKSUMTYPE="MD5" SIZE="693096">
				<FLocat LOCTYPE="URL" xlink:href="file://./0004.xml"/>
			</file>
		</fileGrp>
	</fileSec>
	<structMap LABEL="Physical Structure" TYPE="PHYSICAL">
		<div ID="DIVP1" DMDID="MODSMD_ELEC MODSMD_PRINT" LABEL="New Zealand Gazette and Wellington Spectator New Zealand Gazette;New Zealand Gazette and Britannia Spectator;Wellington Spectator;Britannia Spectator" TYPE="Newspaper">
			<div ID="DIVP2" ORDER="1" TYPE="PAGE">
				<fptr>
					<par>
						<area FILEID="IMG00001"/>
						<area FILEID="ALTO0001" BETYPE="IDREF" BEGIN="P1"/>
					</par>
				</fptr>
			</div>
			<div ID="DIVP3" ORDER="2" TYPE="PAGE">
				<fptr>
					<par>
						<area FILEID="IMG00002"/>
						<area FILEID="ALTO0002" BETYPE="IDREF" BEGIN="P2"/>
					</par>
				</fptr>
			</div>
			<div ID="DIVP4" ORDER="3" TYPE="PAGE">
				<fptr>
					<par>
						<area FILEID="IMG00003"/>
						<area FILEID="ALTO0003" BETYPE="IDREF" BEGIN="P3"/>
					</par>
				</fptr>
			</div>
			<div ID="DIVP5" ORDER="4" TYPE="PAGE">
				<fptr>
					<par>
						<area FILEID="IMG00004"/>
						<area FILEID="ALTO0004" BETYPE="IDREF" BEGIN="P4"/>
					</par>
				</fptr>
			</div>
		</div>
	</structMap>
	<structMap LABEL="Logical Structure" TYPE="LOGICAL">
		<div ID="DIVL1" TYPE="Newspaper" LABEL="New Zealand Gazette and Wellington Spectator no. 177 1842-09-17">
			<div ID="DIVL2" TYPE="VOLUME" DMDID="MODSMD_PRINT MODSMD_ELEC" LABEL="New Zealand Gazette and Wellington Spectator no. 177 1842-09-17">
				<div ID="DIVL3" TYPE="ISSUE" DMDID="MODSMD_ISSUE1" LABEL="New Zealand Gazette and Wellington Spectator New Zealand Gazette;New Zealand Gazette and Britannia Spectator;Wellington Spectator;Britannia Spectator no. 177 1842-09-17">
					<div ID="DIVL4" TYPE="CONTENT">
						<div ID="DIVL5" TYPE="ARTICLE" DMDID="MODSMD_ARTICLE1" LABEL="THE NEW ZEALAND GAZETTE AND">
							<div ID="DIVL6" TYPE="HEADING">
								<div ID="DIVL7" TYPE="TITLE">
									<fptr>
										<area BETYPE="IDREF" FILEID="ALTO0001" BEGIN="P1_TB00001"/>
									</fptr>
								</div>
								<div ID="DIVL8" TYPE="TEXT">
									<fptr>
										<seq>
											<area BETYPE="IDREF" FILEID="ALTO0001" BEGIN="P1_TB00005"/>
											<area BETYPE="IDREF" FILEID="ALTO0001" BEGIN="P1_TB00004"/>
											<area BETYPE="IDREF" FILEID="ALTO0001" BEGIN="P1_TB00002"/>
											<area BETYPE="IDREF" FILEID="ALTO0001" BEGIN="P1_TB00003"/>
										</seq>
									</fptr>
								</div>
							</div>
						</div>
						<div ID="DIVL9" TYPE="ARTICLE" DMDID="MODSMD_ARTICLE2" LABEL="SHIPPING INTELLIGENCE.">
							<div ID="DIVL10" TYPE="HEADING">
								<div ID="DIVL11" TYPE="TITLE">
									<fptr>
										<area BETYPE="IDREF" FILEID="ALTO0002" BEGIN="P2_TB00026"/>
									</fptr>
								</div>
								<div ID="DIVL12" TYPE="TEXT">
									<fptr>
										<area BETYPE="IDREF" FILEID="ALTO0002" BEGIN="P2_TB00030"/>
									</fptr>
								</div>
							</div>
							<div ID="DIVL13" TYPE="BODY">
								<div ID="DIVL14" TYPE="BODY_CONTENT">
									<div ID="DIVL15" TYPE="PARAGRAPH" ORDER="1">
										<div ID="DIVL16" TYPE="TEXT">
											<fptr>
												<area BETYPE="IDREF" FILEID="ALTO0002" BEGIN="P2_TB00031"/>
											</fptr>
										</div>
									</div>
									<div ID="DIVL17" TYPE="PARAGRAPH" ORDER="2">
										<div ID="DIVL18" TYPE="TEXT">
											<fptr>
												<area BETYPE="IDREF" FILEID="ALTO0002" BEGIN="P2_TB00004"/>
											</fptr>
										</div>
									</div>
								</div>
							</div>
						</div>
						<div ID="DIVL19" TYPE="ARTICLE" DMDID="MODSMD_ARTICLE3" LABEL="IN PORT.">
							<div ID="DIVL20" TYPE="HEADING">
								<div ID="DIVL21" TYPE="TITLE">
									<fptr>
										<area BETYPE="IDREF" FILEID="ALTO0002" BEGIN="P2_TB00009"/>
									</fptr>
								</div>
							</div>
							<div ID="DIVL22" TYPE="BODY">
								<div ID="DIVL23" TYPE="BODY_CONTENT">
									<div ID="DIVL24" TYPE="PARAGRAPH" ORDER="1">
										<div ID="DIVL25" TYPE="TEXT">
											<fptr>
												<area BETYPE="IDREF" FILEID="ALTO0002" BEGIN="P2_TB00010"/>
											</fptr>
										</div>
									</div>
									<div ID="DIVL26" TYPE="PARAGRAPH" ORDER="2">
										<div ID="DIVL27" TYPE="TEXT">
											<fptr>
												<area BETYPE="IDREF" FILEID="ALTO0002" BEGIN="P2_TB00011"/>
											</fptr>
										</div>
									</div>
									<div ID="DIVL28" TYPE="PARAGRAPH" ORDER="3">
										<div ID="DIVL29" TYPE="TEXT">
											<fptr>
												<area BETYPE="IDREF" FILEID="ALTO0002" BEGIN="P2_TB00012"/>
											</fptr>
										</div>
									</div>
									<div ID="DIVL30" TYPE="PARAGRAPH" ORDER="4">
										<div ID="DIVL31" TYPE="TEXT">
											<fptr>
												<area BETYPE="IDREF" FILEID="ALTO0002" BEGIN="P2_TB00013"/>
											</fptr>
										</div>
									</div>
									<div ID="DIVL32" TYPE="PARAGRAPH" ORDER="5">
										<div ID="DIVL33" TYPE="TEXT">
											<fptr>
												<area BETYPE="IDREF" FILEID="ALTO0002" BEGIN="P2_TB00014"/>
											</fptr>
										</div>
									</div>
									<div ID="DIVL34" TYPE="PARAGRAPH" ORDER="6">
										<div ID="DIVL35" TYPE="TEXT">
											<fptr>
												<area BETYPE="IDREF" FILEID="ALTO0002" BEGIN="P2_TB00015"/>
											</fptr>
										</div>
									</div>
								</div>
							</div>
						</div>
						<div ID="DIVL36" TYPE="ARTICLE" DMDID="MODSMD_ARTICLE4" LABEL="CUSTOM HOUSE.">
							<div ID="DIVL37" TYPE="HEADING">
								<div ID="DIVL38" TYPE="TITLE">
									<fptr>
										<area BETYPE="IDREF" FILEID="ALTO0002" BEGIN="P2_TB00016"/>
									</fptr>
								</div>
								<div ID="DIVL39" TYPE="TEXT">
									<fptr>
										<area BETYPE="IDREF" FILEID="ALTO0002" BEGIN="P2_TB00018"/>
									</fptr>
								</div>
							</div>
							<div ID="DIVL40" TYPE="BODY">
								<div ID="DIVL41" TYPE="BODY_CONTENT">
									<div ID="DIVL42" TYPE="PARAGRAPH" ORDER="1">
										<div ID="DIVL43" TYPE="TEXT">
											<fptr>
												<area BETYPE="IDREF" FILEID="ALTO0002" BEGIN="P2_TB00019"/>
											</fptr>
										</div>
									</div>
									<div ID="DIVL44" TYPE="PARAGRAPH" ORDER="2">
										<div ID="DIVL45" TYPE="TEXT">
											<fptr>
												<seq>
													<area BETYPE="IDREF" FILEID="ALTO0002" BEGIN="P2_TB00021"/>
													<area BETYPE="IDREF" FILEID="ALTO0002" BEGIN="P2_TB00027"/>
												</seq>
											</fptr>
										</div>
									</div>
									<div ID="DIVL46" TYPE="PARAGRAPH" ORDER="3">
										<div ID="DIVL47" TYPE="TEXT">
											<fptr>
												<area BETYPE="IDREF" FILEID="ALTO0002" BEGIN="P2_TB00028"/>
											</fptr>
										</div>
									</div>
								</div>
							</div>
						</div>
						<div ID="DIVL48" TYPE="ARTICLE" DMDID="MODSMD_ARTICLE5" LABEL="METEOROLOGICAL TABLE.">
							<div ID="DIVL49" TYPE="HEADING">
								<div ID="DIVL50" TYPE="TITLE">
									<fptr>
										<area BETYPE="IDREF" FILEID="ALTO0002" BEGIN="P2_TB00029"/>
									</fptr>
								</div>
								<div ID="DIVL51" TYPE="TEXT">
									<fptr>
										<area BETYPE="IDREF" FILEID="ALTO0002" BEGIN="P2_TB00032"/>
									</fptr>
								</div>
							</div>
							<div ID="DIVL52" TYPE="BODY">
								<div ID="DIVL53" TYPE="TABLE" ORDER="1" DMDID="MODSMD_PICT1" LABEL="Untitled">
									<div ID="DIVL54" TYPE="IMAGE">
										<fptr>
											<area BETYPE="IDREF" FILEID="ALTO0002" BEGIN="P2_CB00001"/>
										</fptr>
									</div>
								</div>
							</div>
						</div>
						<div ID="DIVL55" TYPE="ARTICLE" DMDID="MODSMD_ARTICLE6" LABEL="New Zealand Gazette">
							<div ID="DIVL56" TYPE="HEADING">
								<div ID="DIVL57" TYPE="TITLE">
									<fptr>
										<area BETYPE="IDREF" FILEID="ALTO0002" BEGIN="P2_TB00007"/>
									</fptr>
								</div>
								<div ID="DIVL58" TYPE="TEXT">
									<fptr>
										<area BETYPE="IDREF" FILEID="ALTO0002" BEGIN="P2_TB00006"/>
									</fptr>
								</div>
							</div>
							<div ID="DIVL59" TYPE="BODY">
								<div ID="DIVL60" TYPE="BODY_CONTENT">
									<div ID="DIVL61" TYPE="PARAGRAPH" ORDER="1">
										<div ID="DIVL62" TYPE="TEXT">
											<fptr>
												<area BETYPE="IDREF" FILEID="ALTO0002" BEGIN="P2_TB00008"/>
											</fptr>
										</div>
									</div>
									<div ID="DIVL63" TYPE="PARAGRAPH" ORDER="2">
										<div ID="DIVL64" TYPE="TEXT">
											<fptr>
												<seq>
													<area BETYPE="IDREF" FILEID="ALTO0002" BEGIN="P2_TB00020"/>
													<area BETYPE="IDREF" FILEID="ALTO0002" BEGIN="P2_TB00017"/>
												</seq>
											</fptr>
										</div>
									</div>
									<div ID="DIVL65" TYPE="PARAGRAPH" ORDER="3">
										<div ID="DIVL66" TYPE="TEXT">
											<fptr>
												<area BETYPE="IDREF" FILEID="ALTO0002" BEGIN="P2_TB00023"/>
											</fptr>
										</div>
									</div>
									<div ID="DIVL67" TYPE="PARAGRAPH" ORDER="4">
										<div ID="DIVL68" TYPE="TEXT">
											<fptr>
												<area BETYPE="IDREF" FILEID="ALTO0002" BEGIN="P2_TB00022"/>
											</fptr>
										</div>
									</div>
									<div ID="DIVL69" TYPE="PARAGRAPH" ORDER="5">
										<div ID="DIVL70" TYPE="TEXT">
											<fptr>
												<area BETYPE="IDREF" FILEID="ALTO0002" BEGIN="P2_TB00001"/>
											</fptr>
										</div>
									</div>
									<div ID="DIVL71" TYPE="PARAGRAPH" ORDER="6">
										<div ID="DIVL72" TYPE="TEXT">
											<fptr>
												<area BETYPE="IDREF" FILEID="ALTO0002" BEGIN="P2_TB00002"/>
											</fptr>
										</div>
									</div>
									<div ID="DIVL73" TYPE="PARAGRAPH" ORDER="7">
										<div ID="DIVL74" TYPE="TEXT">
											<fptr>
												<area BETYPE="IDREF" FILEID="ALTO0002" BEGIN="P2_TB00003"/>
											</fptr>
										</div>
									</div>
								</div>
							</div>
						</div>
						<div ID="DIVL75" TYPE="ARTICLE" DMDID="MODSMD_ARTICLE7" LABEL="PUBLIC MEETING.">
							<div ID="DIVL76" TYPE="HEADING">
								<div ID="DIVL77" TYPE="TITLE">
									<fptr>
										<area BETYPE="IDREF" FILEID="ALTO0002" BEGIN="P2_TB00005"/>
									</fptr>
								</div>
							</div>
							<div ID="DIVL78" TYPE="BODY">
								<div ID="DIVL79" TYPE="BODY_CONTENT">
									<div ID="DIVL80" TYPE="PARAGRAPH" ORDER="1">
										<div ID="DIVL81" TYPE="TEXT">
											<fptr>
												<seq>
													<area BETYPE="IDREF" FILEID="ALTO0002" BEGIN="P2_TB00024"/>
													<area BETYPE="IDREF" FILEID="ALTO0003" BEGIN="P3_TB00005"/>
												</seq>
											</fptr>
										</div>
									</div>
								</div>
							</div>
						</div>
						<div ID="DIVL82" TYPE="ARTICLE" DMDID="MODSMD_ARTICLE8" LABEL="EXTRACTS.">
							<div ID="DIVL83" TYPE="HEADING">
								<div ID="DIVL84" TYPE="TITLE">
									<fptr>
										<area BETYPE="IDREF" FILEID="ALTO0003" BEGIN="P3_TB00006"/>
									</fptr>
								</div>
							</div>
							<div ID="DIVL85" TYPE="BODY">
								<div ID="DIVL86" TYPE="BODY_CONTENT">
									<div ID="DIVL87" TYPE="PARAGRAPH" ORDER="1">
										<div ID="DIVL88" TYPE="TEXT">
											<fptr>
												<seq>
													<area BETYPE="IDREF" FILEID="ALTO0003" BEGIN="P3_TB00007"/>
													<area BETYPE="IDREF" FILEID="ALTO0003" BEGIN="P3_TB00003"/>
													<area BETYPE="IDREF" FILEID="ALTO0003" BEGIN="P3_TB00002"/>
													<area BETYPE="IDREF" FILEID="ALTO0003" BEGIN="P3_TB00001"/>
												</seq>
											</fptr>
										</div>
									</div>
									<div ID="DIVL89" TYPE="PARAGRAPH" ORDER="2">
										<div ID="DIVL90" TYPE="TEXT">
											<fptr>
												<seq>
													<area BETYPE="IDREF" FILEID="ALTO0004" BEGIN="P4_TB00006"/>
													<area BETYPE="IDREF" FILEID="ALTO0004" BEGIN="P4_TB00001"/>
												</seq>
											</fptr>
										</div>
									</div>
									<div ID="DIVL91" TYPE="PARAGRAPH" ORDER="3">
										<div ID="DIVL92" TYPE="TEXT">
											<fptr>
												<seq>
													<area BETYPE="IDREF" FILEID="ALTO0004" BEGIN="P4_TB00003"/>
													<area BETYPE="IDREF" FILEID="ALTO0004" BEGIN="P4_TB00002"/>
												</seq>
											</fptr>
										</div>
									</div>
								</div>
							</div>
						</div>
						<div ID="DIVL93" TYPE="SECTION" DMDID="MODSMD_SECTION1">
							<div ID="DIVL94" TYPE="BODY">
								<div ID="DIVL95" TYPE="BODY_CONTENT">
									<div ID="DIVL96" TYPE="ADVERTISEMENT" ORDER="1" LABEL="Adv. 1 Page 1">
										<fptr>
											<area BETYPE="IDREF" FILEID="ALTO0001" BEGIN="P1_CB00003"/>
										</fptr>
									</div>
									<div ID="DIVL97" TYPE="ADVERTISEMENT" ORDER="2" LABEL="Adv. 2 Page 1">
										<fptr>
											<area BETYPE="IDREF" FILEID="ALTO0001" BEGIN="P1_CB00004"/>
										</fptr>
									</div>
									<div ID="DIVL98" TYPE="ADVERTISEMENT" ORDER="3" LABEL="Adv. 3 Page 1">
										<fptr>
											<area BETYPE="IDREF" FILEID="ALTO0001" BEGIN="P1_CB00001"/>
										</fptr>
									</div>
									<div ID="DIVL99" TYPE="ADVERTISEMENT" ORDER="4" LABEL="Adv. 4 Page 1">
										<fptr>
											<area BETYPE="IDREF" FILEID="ALTO0001" BEGIN="P1_CB00002"/>
										</fptr>
									</div>
									<div ID="DIVL100" TYPE="ADVERTISEMENT" ORDER="5" LABEL="Adv. 5 Page 2">
										<fptr>
											<area BETYPE="IDREF" FILEID="ALTO0002" BEGIN="P2_CB00002"/>
										</fptr>
									</div>
								</div>
							</div>
						</div>
					</div>
				</div>
			</div>
		</div>
	</structMap>
</mets>
